Workbook

Sheet Вопросы
A1: № | B1: Источник | C1: Раздел БТ (связка) | D1: Ссылка | E1: Дата | F1: Кто задал | G1: Направление | H1: Кому адресован (функция-ответчик) | I1: Вопрос | J1: Есть ответ | K1: Кто ответил | L1: Ответ | M1: Статус треда | N1: Примечание
A2: 1 | B2: БТ (Google Doc) — комментарий | C2: 6.1 Оформление возврата онлайн / FR-1.4 (отмена возврата) | D2: Открыть комментарий | E2: 28.08.2026 | F2: Мария Мезинова | G2: 1С / товародвижение | H2: Бизнес-заказчик / владелец процесса возвратов; Продукт МП / сайт (UX, макеты) - Роман Пушкарь, Оля Соколова | I2: Мы будем давать возможность корректировки возврата после создания? Или в случае корректировки старый будем удалять и создавать новый? | J2: Нет | M2: Открыт | N2: В документе Е. Лемешевой (вопр. 27, 10) зафиксировано: изменения только через Дружбу либо отмена и новая заявка.
A3: 2 | B3: БТ (Google Doc) — комментарий | C3: 7.5 FR-5.2 Результат экспертизы фиксируется в системе | D3: Открыть комментарий | E3: 27.08.2026 | F3: Мария Мезинова | G3: 1С / товародвижение | H3: Склад (Бетта Про, WMS); 1С / товародвижение - Виталий Рублев | I3: Сейчас при получении данных в 1С о возврате мы от Беты получаем только кондицию брак или недостачи. | J3: Нет | M3: Открыт | N3: Замечание-ограничение: результат экспертизы в 1С сейчас не передаётся полностью.
A4: 3 | B4: БТ (Google Doc) — комментарий | C4: 7.2 FR-2.6 Интеграция склада с курьерской компанией | D4: Открыть комментарий | E4: 28.08.2026 | F4: Мария Мезинова | G4: 1С / товародвижение | H4: IT-архитектура (интеграции) - Предложите | I4: Так мы 1С с курьерскими компаниями интегрируем или систему склада? | J4: Частично | K4: Светлана Варцаба | L4: Как я понимаю, мы 1С интегрируем, и Бетта на своей стороне тоже должна будет сделать какую-то доработку. | M4: Открыт | N4: Требует финального решения по архитектуре интеграции.
A5: 4 | B5: БТ (Google Doc) — комментарий | C5: 6.12 Идентификация на складе по QR/PIN/номеру заказа | D5: Открыть комментарий | E5: 27.08.2026 | F5: Мария Мезинова | G5: 1С / товародвижение | H5: IT-архитектура (интеграции); Склад (Бетта Про, WMS) - Договориться с Виталиев Рублевым | I5: Уже выше задавали вопрос, как эта информация будет считываться Бетой, что будет зашито в этом QR? | J5: Да | K5: Артём Лисин | L5: Описание физики процесса: https://docs.google.com/document/d/1Zmr8Sj2AWePHZbu1j1lDsXq5xoYjoJOm/edit В зависимости от способа забора идентификаторы возврата будут появляться в разный момент времени | M5: Открыт | N5: См. также вопросы Е. Васильевой и А. Колосова по QR (кто генерирует, что зашито).
A6: 5 | B6: БТ (Google Doc) — комментарий | C6: 6.12 Заявление автоматически попадает в WMS в момент оформления (зачёркнуто) | D6: Открыть комментарий | E6: 27.08.2026 | F6: Мария Мезинова | G6: 1С / товародвижение | H6: IT-архитектура (интеграции) - Предложите как надо | I6: У нас нет интеграции сайт — Бета, возврат в Бету попадет только через 1С. И это точно будет не в момент оформления. | J6: Да | K6: Светлана Варцаба | L6: Маша, это отменяю — не нужно заявление на возврат Бетте. | M6: Открыт | N6: Требование снято (в БТ зачёркнуто).
A7: 6 | B7: БТ (Google Doc) — комментарий | C7: 10 Статусная модель возврата | D7: Открыть комментарий | E7: 27.08.2026 | F7: Мария Мезинова | G7: 1С / товародвижение | H7: IT-архитектура (интеграции) Артем Колосов + Виталий Рублев (клиентские статусы даны) | I7: Нужна статусная модель по всем системам, включая ТК и 3PL. Желаемые статусы нужно наложить на физический процесс и статусы партнеров. | J7: Частично | M7: Открыт | N7: Светлана в треде А. Колосова: «Тут блок перепишем».
A8: 7 | B8: БТ (Google Doc) — комментарий | C8: 7.8 FR-8.5 Интеграции с партнёрами доставки / 6.12 | D8: Открыть комментарий | E8: 27.08.2026 | F8: Мария Мезинова | G8: 1С / товародвижение | H8: IT-архитектура (интеграции) Аретм Колосов; Логистика (ТК, ПВЗ, Почта России) Артем Лисин | I8: В какой момент должна срабатывать интеграция 1С-ТК? На каком этапе возврата? | J8: Нет | M8: Открыт
A9: 8 | B9: БТ (Google Doc) — комментарий | C9: 6.3 Канал — розничный магазин (приёмка изделия) | D9: Открыть комментарий | E9: 27.08.2026 | F9: Мария Мезинова | G9: 1С / товародвижение | H9: Александ Ольховиков | I9: Мы планируем приемку по КМ в магазине? Сейчас КМ не проверяем. Если клиент ранее приобрел две одинаковые вещи разными ЗК, мы формируем возврат без проверки КМ. Что КМ из другого ЗК узнаем при приемке на Бете, если товар был туда отправлен. | J9: Да | K9: Артём Колосов | L9: Сейчас магазины при приёмке возврата обязательно сканируют марки, если марки нет - её заново печают по данным из документа продажи и сканируют в возврат. https://wiki.yandex.ru/teams/retail/wiki/instrukcii-roznichnojj-seti/arm-vozvratov.-opisanie-oformlenija-vozvrata-v-nr/ https://wiki.yandex.ru/documentation/user/roznica/russia/kassovaja-disciplina/vozvraty/instrukcija-dlja-arm-vozvratov/ | M9: Открыт
A10: 9 | B10: БТ (Google Doc) — комментарий | C10: 6.4 Канал — курьерская доставка (окно с информацией о возврате) | D10: Открыть комментарий | E10: 26.08.2026 | F10: Мария Мезинова | G10: 1С / товародвижение | H10: Предложите решение корректное | I10: В каком статусе в этот момент должен быть документ возврата? | J10: Нет | M10: Открыт
A11: 10 | B11: БТ (Google Doc) — комментарий | C11: 3.1 Причины возврата | D11: Открыть комментарий | E11: 27.08.2026 | F11: Мария Мезинова | G11: 1С / товародвижение | H11: 1С / товародвижение; Финансы / бухгалтерия - Анжела Калиева, Ольга Соколова | I11: Нужно ли будет причины возвратов передавать и хранить в 1С? | J11: Да | K11: Светлана Варцаба | L11: Нет такой необходимости (ответ дан в соседнем треде Е. Васильевой, т.к. исходный ответ случайно удалён). | M11: Решён
A12: 11 | B12: БТ (Google Doc) — комментарий | C12: 2 Цели и бизнес-метрики (авторазбор аномалий) | D12: Открыть комментарий | E12: 26.08.2026 | F12: Мария Мезинова | G12: 1С / товародвижение | H12: Владелец процесса возвратов; Склад (Бетта Про, WMS); 1С / товародвижение | I12: Что мы вкладываем в «авторазбор аномалий»? Как должен выглядеть этот процесс? | J12: Да | K12: Светлана Варцаба | L12: Разбор аномалий оставляем в текущем состоянии | M12: Открыт
A13: 12 | B13: БТ (Google Doc) — комментарий | C13: 3.1 Функционал Дружбы в RCRM для оформления возврата | D13: Открыть комментарий | E13: 27.08.2026 | F13: Мария Мезинова | G13: 1С / товародвижение | H13: Владелец процесса возвратов; Клиентский сервис (Дружба, Retail CRM) - Варцаба (встреча стоит) | I13: Это будет единственный способ оформления возврата? Будет ли он обязательным? (сейчас есть случаи, когда возврат приходит на склад без оформленного возврата в приложении/RCRM). | J13: Да | K13: Светлана Варцаба | L13: Не единственный — клиент может обратиться в Дружбу, что хочет оформить возврат; у Дружбы должен быть функционал (в RCRM — с возможностью оформить возврат). | M13: Открыт
A14: 13 | B14: БТ (Google Doc) — комментарий | C14: 3.1 Функционал Дружбы в RCRM / 9 Интеграции (CRM) | D14: Открыть комментарий | E14: 27.08.2026 | F14: Мария Мезинова | G14: 1С / товародвижение | H14: IT-архитектура (интеграции) Максим Маринин | I14: Сейчас мы принимаем RCRM как мастер-систему, все спорные кейсы всегда проверяем и сравниваем именно с ней. Какую систему рассматриваем как мастер-систему в этом проекте? | J14: Нет | K14: Светлана Варцаба | L14: Здесь не понимаю, приведи пример, пожалуйста. | M14: Открыт | N14: Нужен пример от Марии; решение по мастер-системе не принято.
A15: 14 | B15: БТ (Google Doc) — комментарий | C15: 3.1 Отказ от бумажного заявления / электронное заявление | D15: Открыть комментарий | E15: 27.08.2026 | F15: Екатерина Лемешева | G15: Аналитик МП / сайт | H15: - | I15: В какой системе генерируется электронное заявление, так как подтвердилось, что оно должно храниться? | J15: Да | K15: Светлана Варцаба | L15: Оно должно создаваться в приложении/на сайте, не храним | M15: Открыт | N15: Мастер-система хранения не определена (см. также вопр. 4 в док. Е. Лемешевой).
A16: 15 | B16: БТ (Google Doc) — комментарий | C16: 3.1 Передача заявления в WMS / 1С (зачёркнуто) | D16: Открыть комментарий | E16: 27.08.2026 | F16: Мария Мезинова | G16: 1С / товародвижение | H16: Юристы; Бизнес-заказчик / владелец процесса возвратов | I16: 25.08 обсуждали, что будет только возврат как документ, заявления не будет. Его не нужно будет хранить и передавать? | J16: Да | K16: Светлана Варцаба | L16: Заявления в электронном виде остаются исключительно для разрешения споров — они должны сохраняться 5 лет (пока не понятно где именно). Хранить нужно, передавать между системами — нет. | M16: Открыт
A17: 16 | B17: БТ (Google Doc) — комментарий | C17: 8 NFR-1 Пиковая нагрузка (всплеск после выходных) | D17: Открыть комментарий | E17: 26.08.2026 | F17: Елена Васильева | G17: Tech-аналитик (сайт / интеграции) | H17: Бизнес-заказчик / владелец процесса возвратов; Склад (Бетта Про, WMS) Оля Соколова | I17: Какие максимальные значения сейчас наблюдаются после выходных? В пункте 5.1 шаг 1 указывалось 50–80 заявлений, то есть примерно такое кол-во? | J17: Нет | M17: Открыт
A18: 17 | B18: БТ (Google Doc) — комментарий | C18: 7.9 FR-9.1 Система формирует отчёт | D18: Открыть комментарий | E18: 27.08.2026 | F18: Елена Васильева | G18: Tech-аналитик (сайт / интеграции) | H18: Финансы / бухгалтерия; 1С / товародвижение | I18: В какой системе формируется отчёт? | J18: Да | K18: Светлана Варцаба | L18: Qlik / 1С. | M18: Открыт
A19: 18 | B19: БТ (Google Doc) — комментарий | C19: 6.8 Приёмка: при сканировании сотрудник склада видит номер заказа | D19: Открыть комментарий | E19: 26.08.2026 | F19: Елена Васильева | G19: Tech-аналитик (сайт / интеграции) | H19: Логистика (ТК, ПВЗ, Почта России); Склад (Бетта Про, WMS) - Виталий Рублев | I19: Выше уже подсвечивался вопрос по QR-кодам. Сотрудник склада будет сканировать QR-код, полученный от ТК? Но в нём навряд ли зашиты наш номер заказа или данные клиента. | J19: Да | K19: Артём Лисин | L19: Описание физики процесса: https://docs.google.com/document/d/1Zmr8Sj2AWePHZbu1j1lDsXq5xoYjoJOm/edit В зависимости от способа забора идентификаторы возврата будут появляться в разный момент времени | M19: Открыт
A20: 19 | B20: БТ (Google Doc) — комментарий | C20: 6.7 Канал — Почта России (клиент оплачивает расходы по доставке) | D20: Открыть комментарий | E20: 26.08.2026 | F20: Елена Васильева | G20: Tech-аналитик (сайт / интеграции) | H20: Владелец процесса возвратов; Финансы / бухгалтерия - Оля Соколова | I20: Хотелось бы уточнить, оплата доставки на стороне клиента? | J20: Нет | M20: Открыт | N20: В док. Е. Лемешевой (вопр. 23) ответ: доставку оплачивает Компания; при браке — продавец.
A21: 20 | B21: БТ (Google Doc) — комментарий | C21: 6.7 Канал — Почта России (накладную отправят на email) | D21: Открыть комментарий | E21: 26.08.2026 | F21: Елена Васильева | G21: Tech-аналитик (сайт / интеграции) | H21: Логистика (ТК, ПВЗ, Почта России); Разработка сайта / бэкенд Артем Лисин | I21: Отправка накладной на email будет происходить вручную или автоматически? | J21: Нет | M21: Открыт
A22: 21 | B22: БТ (Google Doc) — комментарий | C22: 6.1 Оформление возврата онлайн (QR-код) | D22: Открыть комментарий | E22: 26.08.2026 | F22: Елена Васильева | G22: Tech-аналитик (сайт / интеграции) | H22: IT-архитектура (интеграции); Продукт МП / сайт (UX, макеты) Роман Пушкарь/Артем Лисин | I22: Какая система генерит QR в данном сценарии? Какая информация должна быть зашита в QR? | J22: Да | K22: Артём Лисин | L22: QR генерирует одна из наших систем. По этому QR в магазине подтягивается информация по заявлению на возврат от клиента Описание физики процесса: https://docs.google.com/document/d/1Zmr8Sj2AWePHZbu1j1lDsXq5xoYjoJOm/edit В зависимости от способа забора идентификаторы возврата будут появляться в разный момент времени | M22: Открыт | N22: Частичный ответ дан в других тредах: 5Post передаёт QR и цифровой код, СДЭК — только номер накладной, для магазинов QR генерируем сами.
A23: 22 | B23: БТ (Google Doc) — комментарий | C23: 6.2 / 6.4 Канал — курьерская доставка | D23: Открыть комментарий | E23: 28.08.2026 | F23: Елена Васильева | G23: Tech-аналитик (сайт / интеграции) | H23: Логистика (ТК, ПВЗ, Почта России) Артем Лисин | I23: Курьеры от каких ТК будут задействованы для возвратов? Дополнено: только CDEK и Dalli? | J23: Да | K23: Артем Лисин | L23: Сейчас: СДЭК - вся география(кроме Москвы) Далли Сервис ( Москва) Хотели бы после интеграции: СДЭК - вся география ( кроме Москвы и МО) Далли - (Москва и МО) | M23: Открыт
A24: 23 | B24: БТ (Google Doc) — комментарий | C24: 6.5 Канал — 5POST (клиент показывает сотруднику QR) | D24: Открыть комментарий | E24: 26.08.2026 | F24: Елена Васильева | G24: Tech-аналитик (сайт / интеграции) | H24: IT-архитектура (интеграции); Логистика (ТК, ПВЗ, Почта России) Артем Лисин | I24: Этот QR генерирует какая система? Речь уже не про QR от партнёров, а про какой-то другой? Или опечатка в требованиях? | J24: Да | K24: Артём Лисин | L24: QR генерирует одна из наших систем. По этому QR в магазине подтягивается информация по заявлению на возврат от клиента Описание физики процесса: https://docs.google.com/document/d/1Zmr8Sj2AWePHZbu1j1lDsXq5xoYjoJOm/edit В зависимости от способа забора идентификаторы возврата будут появляться в разный момент времени | M24: Открыт
A25: 24 | B25: БТ (Google Doc) — комментарий | C25: 6.11 CSI и обратная связь | D25: Открыть комментарий | E25: 26.08.2026 | F25: Елена Васильева | G25: Tech-аналитик (сайт / интеграции) | H25: Продукт МП / сайт (UX, макеты); Разработка сайта / бэкенд Роман Пушкарь | I25: [tech] Должна быть интеграция с платформой Отзывов, чтобы результаты опроса приходили на платформу. | J25: Нет | M25: Открыт | N25: Технический комментарий-требование, не вопрос.
A26: 25 | B26: БТ (Google Doc) — комментарий | C26: 3.1 / 6.7 Почта России (список филиалов) | D26: Открыть комментарий | E26: 28.08.2026 | F26: Елена Васильева | G26: Tech-аналитик (сайт / интеграции) | H26: Логистика (ТК, ПВЗ, Почта России); Продукт МП / сайт (UX, макеты) Артем Лисин | I26: [tech] Список филиалов Почты РФ должен приходить из сервиса Логистики? Дополнено 28.08: в макетах нет выбора филиала почты, указано, что клиент может отнести в любой ближайший. То есть список филиалов выводить не нужно? | J26: Нет | M26: Открыт
A27: 26 | B27: БТ (Google Doc) — комментарий | C27: 3.1 Причины возврата | D27: Открыть комментарий | E27: 03.09.2026 | F27: Елена Васильева | G27: Tech-аналитик (сайт / интеграции) | H27: Продукт МП / сайт (UX, макеты); Разработка сайта / бэкенд Роман Пушкарь | I27: 1. [tech] Откуда будут приходить причины возврата? 2. Должны ли они где-то настраиваться? | J27: Частично | K27: Светлана Варцаба; Елена Васильева | L27: Светлана: @r.pushkar — где можем настраивать причины возврата, можем ли дать настройку в админке? Елена (03.09): в админке сайта уже есть группы возврата (1-й уровень) и причины (2-й уровень) — предложение использовать готовый функционал и брать причины из админки сайта. | M27: Открыт | N27: Ожидается подтверждение предложения Елены.
A28: 27 | B28: БТ (Google Doc) — комментарий | C28: 7.2 FR-2.3 При сканировании QR/PIN на складе | D28: Открыть комментарий | E28: 27.08.2026 | F28: Елена Васильева | G28: Tech-аналитик (сайт / интеграции) | H28: IT-архитектура (интеграции); Логистика (ТК, ПВЗ, Почта России); Склад (Бетта Про, WMS) Лисин Артем, Виталий Рублев | I28: 1. Какая система генерирует этот QR-код? ТК это делает при оформлении заявки на возврат? 2. Все ли ТК смогут генерировать QR-код? Нужно прояснить, какие QR-коды на каком этапе будут использоваться. Сотрудник склада будет сканировать QR от ТК или другой? Если другой — на каком этапе он появляется, кто генерирует и не запутается ли склад? | J28: Частично | K28: Светлана Варцаба | L28: 5Post передают QR и цифровой код для сдачи. СДЭК ПВЗ — просто номер накладной (QR не генерит). Для возвратов в магазины мы сами должны генерить QR-код. | M28: Открыт | N28: Не отвечено: что сканирует склад и что зашито в QR.
A29: 28 | B29: БТ (Google Doc) — комментарий | C29: 3.1 Приёмка и экспертиза; возврат ДС | D29: Открыть комментарий | E29: 26.08.2026 | F29: Артём Колосов | G29: Архитектор | H29: Владелец процесса возвратов; Склад (Бетта Про, WMS), Оля Соколова, Виталий Рублев | I29: 1. Нужна ли интеграция с ТК/ПВЗ по статусам, если мы эту информацию клиенту не отображаем? 2. Что происходит, если изделие не прошло экспертизу и мы не принимаем возврат? Что делаем, если аномалия: в заявлении одно изделие, а по факту другое? | J29: Нет | L29: Предложите решение | M29: Решён | N29: Тред закрыт без текстового ответа.
A30: 29 | B30: БТ (Google Doc) — комментарий | C30: 6.8 Статусы возврата / 10 Статусная модель | D30: Открыть комментарий | E30: 27.08.2026 | F30: Артём Колосов | G30: Архитектор | H30: Владелец процесса возвратов; Продукт МП / сайт (UX, макеты) - Предложите решение | I30: 1. Между «Создан» и «На экспертизе» должен быть статус для ТК/ПВЗ/5POST (напр. «В пути»). 2. Статус «Принят» неинформативен, как будто финальный. 3. До «Выполнен» отдельно «ДС возвращены», далее по таймеру закрывать. 4. Что по физике процесса при отклонении возврата? 5. Нужны ли промежуточные статусы от ТК по доставке? | J30: Частично | K30: Екатерина Лемешева; Светлана Варцаба | L30: Екатерина: согласна, нужен статус «Клиент передал товар» → «Товар в пути до склада» → «На экспертизе». Светлана: «Тут блок перепишем». | M30: Открыт | N30: Статусная модель будет переписана.
A31: 30 | B31: БТ (Google Doc) — комментарий | C31: 7.8 FR-8.1 Передача заявления в WMS | D31: Открыть комментарий | E31: 27.08.2026 | F31: Артём Колосов | G31: Архитектор | H31: IT-архитектура (интеграции); Склад (Бетта Про, WMS) | I31: Нужно ли заявление в WMS до передачи клиентом изделий? | J31: Да | K31: Светлана Варцаба | L31: Нет, нам никуда его не нужно передавать. | M31: Открыт
A32: 31 | B32: БТ (Google Doc) — комментарий | C32: 7.3 FR-3.3 Аутлет / «Цветной» | D32: Открыть комментарий | E32: 26.08.2026 | F32: Артём Колосов | G32: Архитектор | H32: Розница (операции магазинов); Бизнес-заказчик / владелец процесса возвратов - Света Варцаба / Сергей Ваганов | I32: Если клиент придёт в магазин с покупкой из аутлета — мы его разворачиваем? | J32: Нет | M32: Открыт
A33: 32 | B33: БТ (Google Doc) — комментарий | C33: 3.1 Отказ от бумажного заявления, QR-код на коробах | D33: Открыть комментарий | E33: 26.08.2026 | F33: Артём Колосов | G33: Архитектор | H33: Склад (Бетта Про, WMS) Виталий Рублев | I33: Откуда он его сканирует? Кто его туда наносит? | J33: Да | K33: Артём Лисин | L33: Описание физики процесса: https://docs.google.com/document/d/1Zmr8Sj2AWePHZbu1j1lDsXq5xoYjoJOm/edit В зависимости от способа забора идентификаторы возврата будут появляться в разный момент времени | M33: Открыт
A34: 33 | B34: БТ (Google Doc) — комментарий | C34: 6.3 Розничный магазин (бумажное заявление не подписывается) | D34: Открыть комментарий | E34: 27.08.2026 | F34: Артём Колосов | G34: Архитектор | H34: Розница (операции магазинов); Юристы - Александр Ольховиков, Сергей Ваганов | I34: Что-то даём вообще клиенту? Или он сдал изделие и просто ждёт, когда вернутся деньги? | J34: Да | K34: Александр Ольховиков | L34: У клиента ничего на руках не остаётся. Ждёт возврата ДС Если клиент наставивает то Заявление | M34: Открыт
A35: 34 | B35: БТ (Google Doc) — комментарий | C35: 5.4 Проблемы клиента (курьерская доставка) | D35: Открыть комментарий | E35: 26.08.2026 | F35: Артём Колосов | G35: Архитектор | H35: Логистика (ТК, ПВЗ, Почта России) | I35: Что тут изменится? | J35: Да | L35: ничего не меняется | M35: Открыт
A36: 35 | B36: БТ (Google Doc) — комментарий | C36: 5.4 Проблемы клиента (возврат ДС и оформление) | D36: Открыть комментарий | E36: 26.08.2026 | F36: Артём Колосов | G36: Архитектор | H36: Финансы / бухгалтерия | I36: Как эти проблемы устранит целевой процесс? | J36: Нет | M36: Открыт
A37: 36 | B37: БТ (Google Doc) — комментарий | C37: 4 Роли — Склад Бетта Про (идентификация по QR/PIN) | D37: Открыть комментарий | E37: 26.08.2026 | F37: Артём Колосов | G37: Архитектор | H37: IT-архитектура (интеграции); Склад (Бетта Про, WMS) | I37: Откуда у Бетты возьмутся QR и PIN, они же нужны только на этапе сдачи? | J37: Да | K37: Артём Лисин | L37: Описание физики процесса: https://docs.google.com/document/d/1Zmr8Sj2AWePHZbu1j1lDsXq5xoYjoJOm/edit В зависимости от способа забора идентификаторы возврата будут появляться в разный момент времени | M37: Открыт
A38: 37 | B38: БТ (Google Doc) — комментарий | C38: 4 Роли — Розничный магазин (сканирует QR, экспертиза, подтверждает приёмку) | D38: Открыть комментарий | E38: 26.08.2026 | F38: Артём Колосов | G38: Архитектор | H38: Розница (операции магазинов) Сергей Ваганов / Александр Ольховиков | I38: Есть ли временной лаг в РМ между приёмкой от клиента, экспертизой и подтверждением приёмки? Или это одно действие в системе — приёмка? | J38: Да | K38: Розница (операции магазинов) Сергей Ваганов / Александр Ольховиков | L38: Экспертиза проводится перед оформлением возврата в системе. Считаем, что временного лага нет | M38: Открыт
A39: 38 | B39: БТ (Google Doc) — комментарий | C39: 3.1 Функционал Дружбы в RCRM | D39: Открыть комментарий | E39: 27.08.2026 | F39: Артём Колосов | G39: Архитектор | H39: Клиентский сервис (Дружба, Retail CRM) - Ольга Соколова | I39: Где-то есть его описание? Как видим процесс, что нужно доработать? | J39: Нет | K39: Светлана Варцаба | L39: Здесь я уточню 31.08 с Retail CRM. | M39: Открыт | N39: Ответ отложен.
A40: 39 | B40: БТ (Google Doc) — комментарий | C40: 11 Отчётность — признак исключения/аномалии и её причина | D40: Открыть комментарий | E40: 27.08.2026 | F40: Артём Колосов | G40: Архитектор | H40: 1С / товародвижение; Склад (Бетта Про, WMS) | I40: Есть ли такая информация сейчас где-то? WMS или 1С? | J40: Да | K40: Мария Мезинова | L40: Нет, в 1С видим только брак и недостачи; можем подсветить проблемные документы, по которым не прошла обработка в 1С. Аномалии Бета откладывает у себя и передаёт на разбор в товародвижение; по результатам разбора товародвижение по кнопке в возврате в 1С закрывает документ. | M40: Открыт
A41: 40 | B41: БТ (Google Doc) — комментарий | C41: 11 Отчётность — текущий статус и даты событий | D41: Открыть комментарий | E41: 26.08.2026 | F41: Артём Колосов | G41: Архитектор | H41: Финансы / бухгалтерия; Владелец процесса возвратов; Оля Соколова, Лариса Прокопенко | I41: Выводим текущий статус и его дату изменения, или все возможные статусы и даты их установки? | J41: Нет | M41: Открыт
A42: 41 | B42: БТ (Google Doc) — комментарий | C42: 3.1 Автосверка манифеста | D42: Открыть комментарий | E42: 28.08.2026 | F42: Артём Колосов | G42: Архитектор | H42: 1С / товародвижение; Финансы / бухгалтерия; Оля Соколова , Артем Лисин, Лариса Прокопенко | I42: Что за процесс? Что является результатом автосверки? | J42: Частично | K42: Светлана Варцаба; Мария Мезинова | L42: Светлана: сейчас сверяем манифесты и принятое складом, чтобы понять, кому пора возвращать деньги; при интеграции курьерских служб по возврату в этом нет необходимости. Мария: необходимость в сверке останется (аномалии, ошибки склада, сбой обмена с 1С) — нужен отчёт: данные манифеста vs фактически принятое на Бете. | M42: Открыт | N42: Разногласие: нужна ли сверка в целевом процессе.
A43: 42 | B43: БТ (Google Doc) — комментарий | C43: 6.10 Обмен / 7.7 | D43: Открыть комментарий | E43: 26.08.2026 | F43: Артём Колосов | G43: Архитектор | H43: Маркетинг / лояльность (бонусы, сертификаты, FnF); Бизнес-заказчик / владелец процесса возвратов | I43: Из этого непонятно, меняется ли что-то в функционале обмена. Нужно ли для FnF менять что-то в обмене, если будут изменения в возврате? | J43: Нет | L43: не меняем процесс обмена в итерации 1 | M43: Открыт
A44: 43 | B44: БТ (Google Doc) — комментарий | C44: 3.1 Генерация QR-кода возврата | D44: Открыть комментарий | E44: 27.08.2026 | F44: Артём Колосов | G44: Архитектор | H44: IT-архитектура (интеграции); Логистика (ТК, ПВЗ, Почта России), Артем Лисин | I44: QR создаётся в зависимости от выбранного канала возврата? При смене канала генерируется новый QR? | J44: Да | K44: Светлана Варцаба | L44: 5Post передают QR и цифровой код; СДЭК ПВЗ — номер накладной; для магазинов QR генерим сами. При смене канала генерируется новый — так как должна быть новая заявка на возврат. | M44: Открыт | N44: Уточняющий вопрос Е. Лемешевой в этом же треде — см. следующую строку.
A45: 44 | B45: БТ (Google Doc) — комментарий | C45: 3.1 Генерация QR-кода возврата | D45: Открыть комментарий | E45: 27.08.2026 | F45: Екатерина Лемешева | G45: Аналитик МП / сайт | H45: Продукт МП / сайт (UX, макеты) Роман Пушкарь / Филатова Катя | I45: То есть, если клиент хочет поменять способ возврата (например, с 5POST на СДЭК), он должен сначала отменить текущую заявку и затем создать новую с новым способом, верно? | J45: Нет | L45: Екатерина Лемешева - в MVP, отменяем первую заявку (в ней скрываем блок штрих-код/QR-код чтобы клиент случайно не показал в канале возврата не то что требуется).Создает новую заявку с нужным ему каналом возврата и новым сформированым штрих-код/QR-код, когда ТК подтвердит заявку и мы получим обновленный статус, например, "Заявка на возврат принята". | M45: Открыт | N45: Уточняющий вопрос в треде А. Колосова; подтверждение не получено.
A46: 45 | B46: БТ (Google Doc) — комментарий | C46: 6.9 Возврат денежных средств / 7.6 FR-6.1 | D46: Открыть комментарий | E46: 27.08.2026 | F46: Екатерина Лемешева | G46: Аналитик МП / сайт | H46: Финансы / бухгалтерия; владелец процесса возвратов | I46: Давайте зафиксируем, что на данном этапе возврат ДС будет делаться вручную через кабинет мерчанта. Т.к. AS IS поведение — или подразумевается автоматизация? | J46: Да | K46: Светлана Варцаба | L46: Да, возврат денежных средств должен быть вручную, но мы должны получать статусы о том, что деньги нами возвращены. | M46: Открыт | N46: Противоречит FR-6.1 (возврат ДС инициируется автоматически) — требует правки БТ.
A47: 46 | B47: БТ (Google Doc) — комментарий | C47: 6.7 Почта России (Калининград) / 6.9 сроки возврата ДС | D47: Открыть комментарий | E47: 20.08.2026 | F47: Екатерина Лемешева | G47: Аналитик МП / сайт | H47: Бизнес-заказчик / владелец процесса возвратов; Логистика (ТК, ПВЗ, Почта России) Роман Пушкарь | I47: В случае с Почтой из Калининграда как рассчитывать срок возврата? Посылка может задержаться, и мы не успеем провести экспертизу и вернём деньги раньше. Может, явно указать на макете? (ссылка на Figma) | J47: Нет | L47: Екатерина Лемешева - Тут ответ получен, т к время отчета пойдет от момента попадания товара на наш склад, то отчет 10 дней на возврат ДС пойдет от этого момента. В оферте ссылаться на 10-дневный срок по ст. 26.1 ЗоЗПП, чтобы клиент не считал срок от момента создания заявки / заявления. Четко прописываем в МП/сайте «Обязанность продавца по возврату денежных средств считается наступившей с момента поступления товара на склад и подтверждения соответствия товара условиям возврата уполномоченным сотрудником». В Калининграде вроде открылся наш магазин | M47: Открыт | N47: В док. Е. Лемешевой (вопр. 19–20): срок возврата ДС считается от поступления на склад + проверки; отображать клиенту.
A48: 47 | B48: БТ (Google Doc) — комментарий | C48: 6.7 Канал — Почта России | D48: Открыть комментарий | E48: 26.08.2026 | F48: Екатерина Лемешева | G48: Аналитик МП / сайт | H48: Продукт МП / сайт (UX, макеты); Логистика (ТК, ПВЗ, Почта России) | I48: В макетах только для Калининграда, верно? Не совсем понятно, что требуется от нашего приложения. 1. Почта — та, которая в профиле, или которую он введёт (нет поля)? 2. Накладная генерируется в нашем приложении — это что-то иное от заявления на возврат? 3. Как определять дату, до которой нужно выполнить возврат? | J48: Нет | L48: Екатерина Лемешева - 1. email берем из заказа. 2. Про накладную не знаю ответа, кто ее создает? В BRD написан пункт: 6.7. Канал — Почта России В окне возврата указано, что накладную отправят на email, указанный при оформлении заказа; клиенту приходит накладная. Кто отправляет эту накладную, если он сдает на Почте? 3. Ответ получен: Калининграда / самостоятельной отправки через Почту России;(14 дней), но не понятно, как мы зафиксируем этот момент, что он его принес и отправил, если мы не интегрируемся с почтой. Если только звонок в Дружбу, чтобы они вручную изменили статус что он "В пути", чтобы по истечени времени автоматически не отменить заявку. | M48: Открыт | N48: Частично закрыто док. Е. Лемешевой (вопр. 13, 25): срок 14 дней; заявление прикладывать не нужно.
A49: 48 | B49: БТ (Google Doc) — комментарий | C49: 6.6 Канал — СДЭК (идентификация по номеру накладной) | D49: Открыть комментарий | E49: 26.08.2026 | F49: Екатерина Лемешева | G49: Аналитик МП / сайт | H49: Логистика (ТК, ПВЗ, Почта России); IT-архитектура (интеграции) - Артм Лисин, Роман Пушкарь | I49: На каком этапе появляется накладная? Должна ли она попасть в МП/сайт, чтобы её видел клиент? Верно ли, что после выбора СДЭК и подтверждения возврата СДЭК получает данные и формирует накладную на своей стороне, а клиент узнаёт номер через приложение СДЭК? Или он должен знать номер через наше МП/сайт? Или имеется в виду «отсканировать штрихкод, полученный от ТК и отображённый в нашем МП/сайте»? | J49: Да | K49: Артём Лисин | L49: "Описание физики процесса: https://docs.google.com/document/d/1Zmr8Sj2AWePHZbu1j1lDsXq5xoYjoJOm/edit В зависимости от способа забора идентификаторы возврата будут появляться в разный момент времени" Екатерина Лемешева - Был ответ, что мы показываем у себя штрих-код и под ним номер накладной. | M49: Открыт
A50: 49 | B50: БТ (Google Doc) — комментарий | C50: 6.5 5POST — уведомление о принятой посылке | D50: Открыть комментарий | E50: 27.08.2026 | F50: Екатерина Лемешева | G50: Аналитик МП / сайт | H50: Логистика (ТК, ПВЗ, Почта России); Артем Лисин | I50: Получает от 5post или от нас? (Елена Васильева: если отправляет 5post, нужны ли настройки на их стороне?) | J50: Частично | K50: Светлана Варцаба | L50: Уточним с коллегами, что будет дешевле (нам самим отправить или через ПВЗ), но вообще лучше, чтобы от нас приходило. | M50: Открыт | N50: Решение не финализировано.
A51: 50 | B51: БТ (Google Doc) — комментарий | C51: 6.5 5POST — клиент следит за статусом | D51: Открыть комментарий | E51: 27.08.2026 | F51: Екатерина Лемешева | G51: Аналитик МП / сайт | H51: Бизнес-заказчик / владелец процесса возвратов; Продукт МП / сайт (UX, макеты) | I51: Следит в каком приложении — у нас или в стороннем сервисе? | J51: Да | K51: Светлана Варцаба | L51: У нас. | M51: Открыт
A52: 51 | B52: БТ (Google Doc) — комментарий | C52: 6.5 5POST — клиент показывает сотруднику QR | D52: Открыть комментарий | E52: 27.08.2026 | F52: Екатерина Лемешева | G52: Аналитик МП / сайт | H52: Логистика (ТК, ПВЗ, Почта России); Продукт МП / сайт (UX, макеты) | I52: Клиент показывает из СМС или из нашего приложения? Должны ли мы отобразить в МП QR/штрихкод, который сгенерировала система 5post? И аналогично СДЭК. | J52: Да | K52: Светлана Варцаба | L52: Да, верно. Он может показать как из СМС, так и из приложения. СДЭК формирует только номер накладной. | M52: Открыт
A53: 52 | B53: БТ (Google Doc) — комментарий | C53: 6.4 Курьер клеит наклейку со штрихкодом | D53: Открыть комментарий | E53: 26.08.2026 | F53: Екатерина Лемешева | G53: Аналитик МП / сайт | H53: Логистика (ТК, ПВЗ, Почта России); IT-архитектура (интеграции) ; Артем Лисин, Виталий Рублев | I53: Где он его генерирует? Это не то же самое, что QR-код, или это штрихкод от транспортной компании, о котором наша система не должна знать? | J53: Да | K53: Артём Лисин | L53: "Описание физики процесса: https://docs.google.com/document/d/1Zmr8Sj2AWePHZbu1j1lDsXq5xoYjoJOm/edit В зависимости от способа забора идентификаторы возврата будут появляться в разный момент времени" | M53: Открыт
A54: 53 | B54: БТ (Google Doc) — комментарий | C54: 6.3 Розничный магазин — сотрудник запрашивает QR | D54: Открыть комментарий | E54: 27.08.2026 | F54: Екатерина Лемешева | G54: Аналитик МП / сайт | H54: Розница (операции магазинов); IT-архитектура (интеграции) | I54: 1. Куда он должен вести или что содержать, чтобы сотрудник его отсканировал и увидел возврат? 2. Правильно ли, что он генерируется только для канала розничного магазина? | J54: Да | K54: Светлана Варцаба | L54: 5Post передают QR и цифровой код; СДЭК ПВЗ — номер накладной; для возвратов в магазины QR генерим сами. Он никуда не должен вести, его должен предъявить клиент (в зависимости от выбранного способа возврата). | M54: Открыт | N54: Содержимое QR для сканера магазина не определено.
A55: 54 | B55: БТ (Google Doc) — комментарий | C55: 3.1 Обмен (онлайн — для FnF) | D55: Открыть комментарий | E55: 31.07.2026 | F55: Светлана Варцаба | G55: Владелец БТ / РП | H55: Бизнес-заказчик / владелец процесса возвратов; Маркетинг / лояльность (бонусы, сертификаты, FnF) | I55: Онлайн обмен для всех, а не только для ФФ. | J55: Нет | M55: Открыт | N55: Заметка владельца БТ — требование к правке документа.
A56: 55 | B56: БТ (Google Doc) — комментарий | C56: 6.10 Обмен / 9 CRM (признак FnF) | D56: Открыть комментарий | E56: 31.07.2026 | F56: Светлана Варцаба | G56: Владелец БТ / РП | H56: Маркетинг / лояльность (бонусы, сертификаты, FnF); Клиентский сервис (Дружба, Retail CRM) | I56: Как мы определим ФФ (если они у нас в гугл-таблице)? | J56: Нет | M56: Открыт
A57: 56 | B57: БТ (Google Doc) — комментарий | C57: 6.9 Возврат денежных средств | D57: Открыть комментарий | E57: 31.07.2026 | F57: Светлана Варцаба | G57: Владелец БТ / РП | H57: Финансы / бухгалтерия; Бизнес-заказчик / владелец процесса возвратов | I57: Идеальный сценарий — у нас есть личный счёт клиента. | J57: Нет | M57: Открыт | N57: Идея, не вопрос.
A58: 57 | B58: БТ (Google Doc) — комментарий | C58: 6.10 Обмен | D58: Открыть комментарий | E58: 31.07.2026 | F58: Светлана Варцаба | G58: Владелец БТ / РП | H58: Бизнес-заказчик / владелец процесса возвратов; Розница (операции магазинов) | I58: Нужно сделать, чтобы можно было поменять — подумать, как сделать как в ЦУМе (вернуть и доплатить). | J58: Нет | M58: Открыт
A59: 58 | B59: БТ (Google Doc) — комментарий | C59: 6.9 Возврат ДС — Бонусы | D59: Открыть комментарий | E59: 31.07.2026 | F59: Светлана Варцаба | G59: Владелец БТ / РП | H59: Маркетинг / лояльность (бонусы, сертификаты, FnF); 1С / товародвижение | I59: Нужно, чтобы автоматически возвращались бонусы; много проблем, так как скидки в разных местах. | J59: Нет | M59: Открыт
A60: 59 | B60: БТ (Google Doc) — комментарий | C60: 6.9 Возврат ДС — Сертификат | D60: Открыть комментарий | E60: 26.08.2026 | F60: Светлана Варцаба | G60: Владелец БТ / РП | H60: Маркетинг / лояльность (бонусы, сертификаты, FnF); Финансы / бухгалтерия | I60: Нужно вернуть на сертификат. | J60: Да | K60: Артём Колосов | L60: + (согласен). | M60: Открыт
A61: 62 | B61: БТ (Google Doc) — комментарий | C61: 3.1 Причины возврата | D61: Открыть комментарий | E61: 01.09.2026 | F61: Мария Мезинова | G61: 1С / товародвижение | H61: 1С / товародвижение; | I61: Будут ли передаваться причины возврата в 1С? | J61: Нет | L61: Предложите решение, не понятно для чего это нужно | M61: Открыт | N61: Ранее (27.08) Светлана отвечала: передавать и хранить в 1С нет необходимости; вопрос задан повторно после появления отчёта по причинам.
A62: 67 | B62: Док. «Вопросы Екатерины Лемешевой» — вводный Q&A | C62: 7.1 FR-1.6 Проверка права на возврат (сроки) | D62: Открыть БТ | F62: Екатерина Лемешева | G62: Аналитик МП / сайт | H62: Юристы | I62: Установлен ли законом обязательный срок, в течение которого клиент должен передать товар после оформления заявления? | J62: Да | K62: Мария | L62: Нет. Мария проверила новые Правила продажи № 657 и не нашла такого срока. Судебной практики или иного регулирования по сроку физической передачи товара в ПВЗ/курьеру после оформления заявления также нет. | M62: Закрыт | N62: 2.4 Способы возврата без выбора даты.
A63: 68 | B63: Док. «Вопросы Екатерины Лемешевой» — вводный Q&A | C63: 7.1 FR-1.6 Проверка права на возврат (сроки) | D63: Открыть БТ | F63: Екатерина Лемешева | G63: Аналитик МП / сайт | H63: Юристы; Бизнес-заказчик / владелец процесса возвратов | I63: Может ли компания самостоятельно установить срок передачи товара после оформления заявки? | J63: Да | K63: Мария; бизнес | L63: Да. Поскольку обязательный срок нормативно не установлен, срок можно определить внутри целевого процесса самостоятельно. Бизнес: даём 14 дней. | M63: Закрыт | N63: 2.4 Способы возврата без выбора даты.
A64: 69 | B64: Док. «Вопросы Екатерины Лемешевой» — вводный Q&A | C64: 6.8 Приёмка, экспертиза и статусы / 6.3 РМ | D64: Открыть БТ | F64: Екатерина Лемешева | G64: Аналитик МП / сайт | H64: Склад (Бетта Про, WMS); Розница (операции магазинов) | I64: Где проводится проверка возвращаемого товара? | J64: Да | K64: Мария | L64: При возврате через курьера/ПВЗ товар на месте не проверяется — проверка после поступления на склад. При возврате в розничный магазин сотрудник проверяет товар при приёме. | M64: Закрыт | N64: 4 Фактическая передача товара.
A65: 70 | B65: Док. «Вопросы Екатерины Лемешевой» — вводный Q&A | C65: 6.7 Почта России / 7.3 FR-3.8 | D65: Открыть БТ | F65: Екатерина Лемешева | G65: Аналитик МП / сайт | H65: Юристы | I65: Кто оплачивает доставку возвращаемого товара при браке? | J65: Да | K65: Мария | L65: Продавец. | M65: Закрыт | N65: 6 Расходы на доставку возврата.
A66: 71 | B66: Док. «Вопросы Екатерины Лемешевой» — вводный Q&A | C66: 6.7 Почта России / 7.3 FR-3.8 | D66: Открыть БТ | F66: Екатерина Лемешева | G66: Аналитик МП / сайт | H66: Юристы; Бизнес-заказчик / владелец процесса возвратов | I66: Кто оплачивает доставку при возврате товара надлежащего качества, который просто не подошёл? | J66: Да | K66: Мария; бизнес | L66: Определяется условиями оферты. Компания вправе закрепить, что доставку оплачивает клиент. Бизнес: решается как сейчас. | M66: Закрыт | N66: 6 Расходы на доставку возврата.
A67: 72 | B67: Док. «Вопросы Екатерины Лемешевой» — вопр. 1 | C67: 6.9 Возврат ДС / 7.6 FR-6.3 (реквизиты счёта) | D67: Открыть БТ | F67: Екатерина Лемешева | G67: Аналитик МП / сайт | H67: Финансы / бухгалтерия | I67: Оставляем ли текущий набор банковских реквизитов при запросе в МП и на сайте: ФИО, БИК, название банка, ИНН банка, номер лицевого счёта, номер банковской карты? | J67: Да | K67: Ответ в документе (бизнес; автор в документе не указан) | L67: Нужны: полное ФИО держателя счёта; БИК банка получателя; номер лицевого счёта физ. лица; номер банковской карты/договора — обязательно, если счёт кредитный (начинается с 30232810…). Если счёт обычный (40817810…), номер карты не обязателен — банк пропустит платёж; для кредитного счёта без номера карты/договора банк отклонит платёж. | M67: Закрыт | N67: 1.1 Состав банковских реквизитов. Название банка и ИНН банка в ответе не упомянуты — уточнить, исключаются ли.
A68: 73 | B68: Док. «Вопросы Екатерины Лемешевой» — вопр. 2 | C68: 6.9 Возврат ДС / 7.6 FR-6.3 | D68: Открыть БТ | F68: Екатерина Лемешева | G68: Аналитик МП / сайт | H68: Финансы / бухгалтерия; Юристы | I68: Относится ли минимальный набор «номер счёта + банк» к данным, которые мы запрашиваем у клиента в МП/на сайте, или только к составу электронного заявления? | J68: Частично | K68: Ответ в документе (бизнес; автор в документе не указан) | L68: Дан единый перечень реквизитов (см. вопр. 1); разделение «запрос в МП» vs «состав заявления» явно не прокомментировано. | M68: Открыт | N68: 1.1 Состав банковских реквизитов.
A69: 74 | B69: Док. «Вопросы Екатерины Лемешевой» — вопр. 3 | C69: 3.1 Отказ от бумажного заявления / электронное заявление | D69: Открыть БТ | F69: Екатерина Лемешева | G69: Аналитик МП / сайт | H69: Бизнес-заказчик / владелец процесса возвратов; Продукт МП / сайт (UX, макеты) | I69: Должен ли клиент иметь возможность скачать сформированное электронное заявление из МП/сайта после его оформления? | J69: Да | K69: Ответ в документе (бизнес; автор в документе не указан) | L69: ДА. Заявления не храним, но даём возможность сформировать как клиенту, так и нам из базы сайта. Скачать должно быть можно. | M69: Закрыт | N69: 1.2 Электронное заявление.
A70: 75 | B70: Док. «Вопросы Екатерины Лемешевой» — вопр. 4 | C70: 3.1 Электронное заявление (хранение) | D70: Открыть БТ | F70: Екатерина Лемешева | G70: Аналитик МП / сайт | H70: IT-архитектура (интеграции); Юристы | I70: Какая система должна быть мастер-системой для хранения электронного заявления? | J70: Да | K70: Ответ в документе (бизнес; автор в документе не указан) | L70: Решили не хранить | M70: Открыт | N70: 1.2 Электронное заявление. Открыт; см. также комментарий Е. Лемешевой в БТ (AAACFDssjVQ) — Светлана: «разбираюсь». Противоречие: в комментариях БТ — хранить 5 лет, в документе — «не храним, формируем из базы сайта».
A71: 76 | B71: Док. «Вопросы Екатерины Лемешевой» — вопр. 5 | C71: 3.1 Электронное заявление (шаблон) | D71: Открыть БТ | F71: Екатерина Лемешева | G71: Аналитик МП / сайт | H71: Юристы; Бизнес-заказчик / владелец процесса возвратов | I71: Какой финальный шаблон электронного заявления используем в целевом процессе с учётом текущего заявления и примера LIME? | J71: Частично | K71: Ответ в документе (бизнес; автор в документе не указан) | L71: Катя приложила (шаблон). Финальное утверждение шаблона не зафиксировано. | M71: Открыт | N71: 1.2 Электронное заявление.
A72: 77 | B72: Док. «Вопросы Екатерины Лемешевой» — вопр. 6 | C72: 7.1 FR-1.6 Проверка права на возврат (сроки) | D72: Открыть БТ | F72: Екатерина Лемешева | G72: Аналитик МП / сайт | H72: Бизнес-заказчик / владелец процесса возвратов; Юристы | I72: Нужно ли учитывать срок 30 дней в каком-либо сценарии, или для всех сценариев период оформления возврата от получения товара — 14 дней, для F&F — 31 день? | J72: Да | K72: Ответ в документе (бизнес; автор в документе не указан) | L72: Все, кроме F&F — 14 дней на подачу заявления с момента доставки заказа клиенту. Для F&F — 30 дней на подачу заявления с момента доставки. | M72: Закрыт | N72: 2.1 Общий срок возврата. В БТ и в вопросе фигурирует 31 день для FnF, в ответе — 30. Требует единой цифры.
A73: 78 | B73: Док. «Вопросы Екатерины Лемешевой» — вопр. 7 | C73: 6.3–6.7 Каналы возврата | D73: Открыть БТ | F73: Екатерина Лемешева | G73: Аналитик МП / сайт | H73: Бизнес-заказчик / владелец процесса возвратов; Логистика (ТК, ПВЗ, Почта России) | I73: Для каких способов возврата клиент должен выбирать конкретную дату передачи товара? (курьер — да; СДЭК ПВЗ, 5Post, розничный магазин, Калининград — нет) | J73: Да | K73: Ответ в документе (бизнес; автор в документе не указан) | L73: Всё верно. Курьер — дата выбирается; СДЭК ПВЗ — нет; 5Post, розничный магазин, Калининград (Почта России самостоятельно) — дата не выбирается, клиент должен отправить/передать возврат в течение 14 дней. | M73: Закрыт | N73: 2.2 Выбор даты передачи.
... A86: 91 | B86: Док. «Вопросы Екатерины Лемешевой» — вопр. 20 | C86: 7.4 FR-4.3 Раздел «Возвраты» | D86: Открыть БТ | F86: Екатерина Лемешева | G86: Аналитик МП / сайт | H86: Продукт МП / сайт (UX, макеты); Юристы | I86: Подтверждаем, что клиенту нужно явно сообщать точку отсчёта срока возврата ДС (поступление на склад + проверка) и отображать это в МП/сайте? | J86: Да | K86: Ответ в документе (бизнес; автор в документе не указан) | L86: Подтверждаем! Делаем аналогично LIME (сроки от даты поступления на склад). | M86: Закрыт | N86: 5 Поступление на склад и возврат денег.
A87: 92 | B87: Док. «Вопросы Екатерины Лемешевой» — вопр. 21 | C87: 7.4 FR-4.3 Раздел «Возвраты» | D87: Открыть БТ | F87: Екатерина Лемешева | G87: Аналитик МП / сайт | H87: Продукт МП / сайт (UX, макеты) Роман Пушкарь / Филатова Катя | I87: Если да, то где на макете должна быть эта надпись / на каком этапе? | J87: Нет | M87: Открыт | N87: 5 Поступление на склад и возврат денег. Открыт.
A88: 93 | B88: Док. «Вопросы Екатерины Лемешевой» — вопр. 22 | C88: 6.3 Розничный магазин / 7.6 | D88: Открыть БТ | F88: Екатерина Лемешева | G88: Аналитик МП / сайт | H88: Розница (операции магазинов); Финансы / бухгалтерия | I88: Для возврата в розничный магазин от какого события начинается 10-дневный срок возврата ДС: от приёма и проверки товара в магазине? | J88: Да | K88: Ответ в документе (бизнес; автор в документе не указан) | L88: Магазин принял возврат. | M88: Закрыт | N88: 5 Поступление на склад и возврат денег.
A89: 94 | B89: Док. «Вопросы Екатерины Лемешевой» — вопр. 23 | C89: 6.7 Почта России / 7.3 FR-3.8 | D89: Открыть БТ | F89: Екатерина Лемешева | G89: Аналитик МП / сайт | H89: Бизнес-заказчик / владелец процесса возвратов; Финансы / бухгалтерия | I89: Кто оплачивает доставку при возврате товара надлежащего качества — клиент или компания? Какое правило закрепляем в целевом процессе и оферте? | J89: Да | K89: Ответ в документе (бизнес; автор в документе не указан) | L89: Компания. | M89: Закрыт | N89: 6.1 Правило оплаты доставки. Расходится с ответом Марии/бизнеса выше («решается как сейчас») и с БТ 6.7 («клиент оплачивает расходы по доставке») — требует единого решения.
A90: 95 | B90: Док. «Вопросы Екатерины Лемешевой» — вопр. 24 | C90: 6.7 / 7.3 FR-3.8 | D90: Открыть БТ | F90: Екатерина Лемешева | G90: Аналитик МП / сайт | H90: Бизнес-заказчик / владелец процесса возвратов | I90: Какие существующие причины возврата должны автоматически означать, что доставка возврата оплачивается продавцом как возврат товара с браком? | J90: Да | K90: Ответ в документе (бизнес; автор в документе не указан) | L90: Любые. | M90: Закрыт | N90: 6.1 Правило оплаты доставки.
A91: 96 | B91: Док. «Вопросы Екатерины Лемешевой» — вопр. 24.1 | C91: 7.5 Приёмка и экспертиза | D91: Открыть БТ | F91: Екатерина Лемешева | G91: Аналитик МП / сайт | H91: Владелец процесса возвратов; Склад (Бетта Про, WMS); Виталий Рублев | I91: На каком этапе считаем, что брак подтверждён и доставка возврата оплачивается продавцом: по выбранной клиентом причине или только после проверки/экспертизы? | J91: Нет | M91: Открыт | N91: 6.1 Правило оплаты доставки. Открыт.
A92: 97 | B92: Док. «Вопросы Екатерины Лемешевой» — вопр. 24.2 | C92: 7.5 FR-5.3 / 5.4 | D92: Открыть БТ | F92: Екатерина Лемешева | G92: Аналитик МП / сайт | H92: Владелец процесса возвратов; Финансы / бухгалтерия; Клиентский сервис (Дружба, Retail CRM) | I92: Если клиент выбрал причину «брак», но по итогам проверки брак не подтвердился — что с оплатой доставки и с процессом в целом? | J92: Частично | K92: Ответ в документе (бизнес; автор в документе не указан) | L92: Обратиться к Оле Соколовой; на первом этапе оставляем решение как есть сейчас. | M92: Открыт | N92: 6.1 Правило оплаты доставки.
A93: 98 | B93: Док. «Вопросы Екатерины Лемешевой» — вопр. 25 | C93: 6.7 Канал — Почта России | D93: Открыть БТ | F93: Екатерина Лемешева | G93: Аналитик МП / сайт | H93: Логистика (ТК, ПВЗ, Почта России); Бизнес-заказчик / владелец процесса возвратов | I93: Правильно ли зафиксирован целевой сценарий для Калининграда: клиент оформляет заявку, скачивает и прикладывает бланк заявления и самостоятельно отправляет товар через Почту России? | J93: Да | K93: Ответ в документе (бизнес; автор в документе не указан) | L93: Клиенту не нужно прикладывать заявление. | M93: Закрыт | N93: 6.2 Калининград.
A94: 99 | B94: Док. «Вопросы Екатерины Лемешевой» — вопр. 26 | C94: 6.7 Канал — Почта России (расходы по доставке) | D94: Открыть БТ | F94: Екатерина Лемешева | G94: Аналитик МП / сайт | H94: Финансы / бухгалтерия; Логистика (ТК, ПВЗ, Почта России); Ольга Соколова, Лариса Прокопенко | I94: Как компенсировать клиенту из Калининграда расход на самостоятельную отправку через Почту России при возврате по браку? (кто платит изначально, как узнаём стоимость, нужен ли чек, способ и момент компенсации, инструкция в карточке возврата) | J94: Нет | M94: Открыт | N94: 6.2 Калининград. Открыт; раздел помечен «уточнить у Оли Соколовой».
A95: 100 | B95: Док. «Вопросы Екатерины Лемешевой» — вопр. 27 | C95: 6.1 / FR-1.4 Отмена возврата | D95: Открыть БТ | F95: Екатерина Лемешева | G95: Аналитик МП / сайт | H95: Бизнес-заказчик / владелец процесса возвратов; Клиентский сервис (Дружба, Retail CRM) | I95: Если после формирования электронного заявления клиент изменяет данные заявки, входящие в заявление — оно обновляется или формируется новая версия? | J95: Да | K95: Ответ в документе (бизнес; автор в документе не указан) | L95: Клиент может внести изменения только через Дружбу либо отменить возврат и оформить заново. Если в заявлении есть данные, которые могут измениться, нужен зафиксированный пример шаблона. | M95: Закрыт | N95: 7 Изменение заявки после формирования заявления.
A96: 101 | B96: Док. «Вопросы Екатерины Лемешевой» — вопр. 28 | C96: 3.1 Электронное заявление (хранение) | D96: Открыть БТ | F96: Екатерина Лемешева | G96: Аналитик МП / сайт | H96: Юристы; IT-архитектура (интеграции) | I96: Что происходит с предыдущей версией заявления: сохраняется или заменяется новой? | J96: Да | K96: Ответ в документе (бизнес; автор в документе не указан) | L96: Сохраняется. | M96: Закрыт | N96: 7 Изменение заявки после формирования заявления.
A97: 102 | B97: Док. «Вопросы Екатерины Лемешевой» — вопр. 29 | C97: 10 Статусная модель / 3.1 Электронное заявление | D97: Открыть БТ | F97: Екатерина Лемешева | G97: Аналитик МП / сайт | H97: Юристы; IT-архитектура (интеграции) | I97: Что происходит с электронным заявлением, если заявка автоматически отменяется из-за непередачи товара в срок? | J97: Да | K97: Ответ в документе (бизнес; автор в документе не указан) | L97: Заявление получает статус отменённого/аннулированного. | M97: Закрыт | N97: 7 Изменение заявки после формирования заявления.
A98: 103 | B98: Док. «Вопросы Екатерины Лемешевой» — вопр. 30 | C98: 3.1 Электронное заявление | D98: Открыть БТ | F98: Екатерина Лемешева | G98: Аналитик МП / сайт | H98: Юристы; IT-архитектура (интеграции) | I98: Если после отмены клиент оформляет новую заявку — формируется новое электронное заявление, а предыдущее сохраняется отдельно? | J98: Да | K98: Ответ в документе (бизнес; автор в документе не указан) | L98: Верно. | M98: Закрыт | N98: 7 Изменение заявки после формирования заявления.

Sheet Сводка
A1: По источнику | B1: Всего | C1: Есть ответ | D1: Частично | E1: Нет ответа
A2: БТ (Google Doc) — комментарии | B2: =COUNTIF('Вопросы'!$B$2:$B$98,"БТ (Google Doc)*") -> 60 | C2: =COUNTIFS('Вопросы'!$B$2:$B$98,"БТ (Google Doc)*",'Вопросы'!$J$2:$J$98,"Да") -> 28 | D2: =COUNTIFS('Вопросы'!$B$2:$B$98,"БТ (Google Doc)*",'Вопросы'!$J$2:$J$98,"Частично") -> 7 | E2: =COUNTIFS('Вопросы'!$B$2:$B$98,"БТ (Google Doc)*",'Вопросы'!$J$2:$J$98,"Нет") -> 25
A3: Документ Е. Лемешевой | B3: =COUNTIF('Вопросы'!$B$2:$B$98,"Док. «Вопросы Екатерины Лемешевой»*") -> 37 | C3: =COUNTIFS('Вопросы'!$B$2:$B$98,"Док. «Вопросы Екатерины Лемешевой»*",'Вопросы'!$J$2:$J$98,"Да") -> 28 | D3: =COUNTIFS('Вопросы'!$B$2:$B$98,"Док. «Вопросы Екатерины Лемешевой»*",'Вопросы'!$J$2:$J$98,"Частично") -> 6 | E3: =COUNTIFS('Вопросы'!$B$2:$B$98,"Док. «Вопросы Екатерины Лемешевой»*",'Вопросы'!$J$2:$J$98,"Нет") -> 3
A4: Итого | B4: =SUM(B2:B3) -> 97 | C4: =SUM(C2:C3) -> 56 | D4: =SUM(D2:D3) -> 13 | E4: =SUM(E2:E3) -> 28
A6: Кто задал | B6: Всего | C6: Есть ответ | D6: Частично | E6: Нет ответа
A7: Мария Мезинова | B7: =COUNTIF('Вопросы'!$F$2:$F$98,"Мария Мезинова") -> 15 | C7: =COUNTIFS('Вопросы'!$F$2:$F$98,"Мария Мезинова",'Вопросы'!$J$2:$J$98,"Да") -> 7 | D7: =COUNTIFS('Вопросы'!$F$2:$F$98,"Мария Мезинова",'Вопросы'!$J$2:$J$98,"Частично") -> 2 | E7: =COUNTIFS('Вопросы'!$F$2:$F$98,"Мария Мезинова",'Вопросы'!$J$2:$J$98,"Нет") -> 6
A8: Елена Васильева | B8: =COUNTIF('Вопросы'!$F$2:$F$98,"Елена Васильева") -> 12 | C8: =COUNTIFS('Вопросы'!$F$2:$F$98,"Елена Васильева",'Вопросы'!$J$2:$J$98,"Да") -> 5 | D8: =COUNTIFS('Вопросы'!$F$2:$F$98,"Елена Васильева",'Вопросы'!$J$2:$J$98,"Частично") -> 2 | E8: =COUNTIFS('Вопросы'!$F$2:$F$98,"Елена Васильева",'Вопросы'!$J$2:$J$98,"Нет") -> 5
A9: Артём Колосов | B9: =COUNTIF('Вопросы'!$F$2:$F$98,"Артём Колосов") -> 16 | C9: =COUNTIFS('Вопросы'!$F$2:$F$98,"Артём Колосов",'Вопросы'!$J$2:$J$98,"Да") -> 8 | D9: =COUNTIFS('Вопросы'!$F$2:$F$98,"Артём Колосов",'Вопросы'!$J$2:$J$98,"Частично") -> 2 | E9: =COUNTIFS('Вопросы'!$F$2:$F$98,"Артём Колосов",'Вопросы'!$J$2:$J$98,"Нет") -> 6
A10: Екатерина Лемешева | B10: =COUNTIF('Вопросы'!$F$2:$F$98,"Екатерина Лемешева") -> 48 | C10: =COUNTIFS('Вопросы'!$F$2:$F$98,"Екатерина Лемешева",'Вопросы'!$J$2:$J$98,"Да") -> 35 | D10: =COUNTIFS('Вопросы'!$F$2:$F$98,"Екатерина Лемешева",'Вопросы'!$J$2:$J$98,"Частично") -> 7 | E10: =COUNTIFS('Вопросы'!$F$2:$F$98,"Екатерина Лемешева",'Вопросы'!$J$2:$J$98,"Нет") -> 6
A11: Светлана Варцаба | B11: =COUNTIF('Вопросы'!$F$2:$F$98,"Светлана Варцаба") -> 6 | C11: =COUNTIFS('Вопросы'!$F$2:$F$98,"Светлана Варцаба",'Вопросы'!$J$2:$J$98,"Да") -> 1 | D11: =COUNTIFS('Вопросы'!$F$2:$F$98,"Светлана Варцаба",'Вопросы'!$J$2:$J$98,"Частично") -> 0 | E11: =COUNTIFS('Вопросы'!$F$2:$F$98,"Светлана Варцаба",'Вопросы'!$J$2:$J$98,"Нет") -> 5
A13: Функция-ответчик (входит в адресаты) | B13: Всего | C13: Есть ответ | D13: Частично | E13: Нет ответа
A14: Бизнес-заказчик / владелец процесса возвратов | B14: =COUNTIF('Вопросы'!$H$2:$H$98,"*Бизнес-заказчик / владелец процесса возвратов*") -> 28 | C14: =COUNTIFS('Вопросы'!$H$2:$H$98,"*Бизнес-заказчик / владелец процесса возвратов*",'Вопросы'!$J$2:$J$98,"Да") -> 17 | D14: =COUNTIFS('Вопросы'!$H$2:$H$98,"*Бизнес-заказчик / владелец процесса возвратов*",'Вопросы'!$J$2:$J$98,"Частично") -> 3 | E14: =COUNTIFS('Вопросы'!$H$2:$H$98,"*Бизнес-заказчик / владелец процесса возвратов*",'Вопросы'!$J$2:$J$98,"Нет") -> 8
A15: IT-архитектура (интеграции) | B15: =COUNTIF('Вопросы'!$H$2:$H$98,"*IT-архитектура (интеграции)*") -> 20 | C15: =COUNTIFS('Вопросы'!$H$2:$H$98,"*IT-архитектура (интеграции)*",'Вопросы'!$J$2:$J$98,"Да") -> 15 | D15: =COUNTIFS('Вопросы'!$H$2:$H$98,"*IT-архитектура (интеграции)*",'Вопросы'!$J$2:$J$98,"Частично") -> 3 | E15: =COUNTIFS('Вопросы'!$H$2:$H$98,"*IT-архитектура (интеграции)*",'Вопросы'!$J$2:$J$98,"Нет") -> 2
A16: Логистика (ТК, ПВЗ, Почта России) | B16: =COUNTIF('Вопросы'!$H$2:$H$98,"*Логистика (ТК, ПВЗ, Почта России)*") -> 21 | C16: =COUNTIFS('Вопросы'!$H$2:$H$98,"*Логистика (ТК, ПВЗ, Почта России)*",'Вопросы'!$J$2:$J$98,"Да") -> 12 | D16: =COUNTIFS('Вопросы'!$H$2:$H$98,"*Логистика (ТК, ПВЗ, Почта России)*",'Вопросы'!$J$2:$J$98,"Частично") -> 3 | E16: =COUNTIFS('Вопросы'!$H$2:$H$98,"*Логистика (ТК, ПВЗ, Почта России)*",'Вопросы'!$J$2:$J$98,"Нет") -> 6
A17: Продукт МП / сайт (UX, макеты) | B17: =COUNTIF('Вопросы'!$H$2:$H$98,"*Продукт МП / сайт (UX, макеты)*") -> 17 | C17: =COUNTIFS('Вопросы'!$H$2:$H$98,"*Продукт МП / сайт (UX, макеты)*",'Вопросы'!$J$2:$J$98,"Да") -> 8 | D17: =COUNTIFS('Вопросы'!$H$2:$H$98,"*Продукт МП / сайт (UX, макеты)*",'Вопросы'!$J$2:$J$98,"Частично") -> 3 | E17: =COUNTIFS('Вопросы'!$H$2:$H$98,"*Продукт МП / сайт (UX, макеты)*",'Вопросы'!$J$2:$J$98,"Нет") -> 6
A18: Финансы / бухгалтерия | B18: =COUNTIF('Вопросы'!$H$2:$H$98,"*Финансы / бухгалтерия*") -> 16 | C18: =COUNTIFS('Вопросы'!$H$2:$H$98,"*Финансы / бухгалтерия*",'Вопросы'!$J$2:$J$98,"Да") -> 8 | D18: =COUNTIFS('Вопросы'!$H$2:$H$98,"*Финансы / бухгалтерия*",'Вопросы'!$J$2:$J$98,"Частично") -> 3 | E18: =COUNTIFS('Вопросы'!$H$2:$H$98,"*Финансы / бухгалтерия*",'Вопросы'!$J$2:$J$98,"Нет") -> 5
A19: Юристы | B19: =COUNTIF('Вопросы'!$H$2:$H$98,"*Юристы*") -> 15 | C19: =COUNTIFS('Вопросы'!$H$2:$H$98,"*Юристы*",'Вопросы'!$J$2:$J$98,"Да") -> 13 | D19: =COUNTIFS('Вопросы'!$H$2:$H$98,"*Юристы*",'Вопросы'!$J$2:$J$98,"Частично") -> 2 | E19: =COUNTIFS('Вопросы'!$H$2:$H$98,"*Юристы*",'Вопросы'!$J$2:$J$98,"Нет") -> 0
A20: Склад (Бетта Про, WMS) | B20: =COUNTIF('Вопросы'!$H$2:$H$98,"*Склад (Бетта Про, WMS)*") -> 14 | C20: =COUNTIFS('Вопросы'!$H$2:$H$98,"*Склад (Бетта Про, WMS)*",'Вопросы'!$J$2:$J$98,"Да") -> 9 | D20: =COUNTIFS('Вопросы'!$H$2:$H$98,"*Склад (Бетта Про, WMS)*",'Вопросы'!$J$2:$J$98,"Частично") -> 1 | E20: =COUNTIFS('Вопросы'!$H$2:$H$98,"*Склад (Бетта Про, WMS)*",'Вопросы'!$J$2:$J$98,"Нет") -> 4
A21: 1С / товародвижение | B21: =COUNTIF('Вопросы'!$H$2:$H$98,"*1С / товародвижение*") -> 8 | C21: =COUNTIFS('Вопросы'!$H$2:$H$98,"*1С / товародвижение*",'Вопросы'!$J$2:$J$98,"Да") -> 4 | D21: =COUNTIFS('Вопросы'!$H$2:$H$98,"*1С / товародвижение*",'Вопросы'!$J$2:$J$98,"Частично") -> 1 | E21: =COUNTIFS('Вопросы'!$H$2:$H$98,"*1С / товародвижение*",'Вопросы'!$J$2:$J$98,"Нет") -> 3
A22: Розница (операции магазинов) | B22: =COUNTIF('Вопросы'!$H$2:$H$98,"*Розница (операции магазинов)*") -> 7 | C22: =COUNTIFS('Вопросы'!$H$2:$H$98,"*Розница (операции магазинов)*",'Вопросы'!$J$2:$J$98,"Да") -> 5 | D22: =COUNTIFS('Вопросы'!$H$2:$H$98,"*Розница (операции магазинов)*",'Вопросы'!$J$2:$J$98,"Частично") -> 0 | E22: =COUNTIFS('Вопросы'!$H$2:$H$98,"*Розница (операции магазинов)*",'Вопросы'!$J$2:$J$98,"Нет") -> 2
A23: Клиентский сервис (Дружба, Retail CRM) | B23: =COUNTIF('Вопросы'!$H$2:$H$98,"*Клиентский сервис (Дружба, Retail CRM)*") -> 7 | C23: =COUNTIFS('Вопросы'!$H$2:$H$98,"*Клиентский сервис (Дружба, Retail CRM)*",'Вопросы'!$J$2:$J$98,"Да") -> 4 | D23: =COUNTIFS('Вопросы'!$H$2:$H$98,"*Клиентский сервис (Дружба, Retail CRM)*",'Вопросы'!$J$2:$J$98,"Частично") -> 1 | E23: =COUNTIFS('Вопросы'!$H$2:$H$98,"*Клиентский сервис (Дружба, Retail CRM)*",'Вопросы'!$J$2:$J$98,"Нет") -> 2
A24: Маркетинг / лояльность (бонусы, сертификаты, FnF) | B24: =COUNTIF('Вопросы'!$H$2:$H$98,"*Маркетинг / лояльность (бонусы, сертификаты, FnF)*") -> 5 | C24: =COUNTIFS('Вопросы'!$H$2:$H$98,"*Маркетинг / лояльность (бонусы, сертификаты, FnF)*",'Вопросы'!$J$2:$J$98,"Да") -> 1 | D24: =COUNTIFS('Вопросы'!$H$2:$H$98,"*Маркетинг / лояльность (бонусы, сертификаты, FnF)*",'Вопросы'!$J$2:$J$98,"Частично") -> 0 | E24: =COUNTIFS('Вопросы'!$H$2:$H$98,"*Маркетинг / лояльность (бонусы, сертификаты, FnF)*",'Вопросы'!$J$2:$J$98,"Нет") -> 4
A25: Разработка сайта / бэкенд | B25: =COUNTIF('Вопросы'!$H$2:$H$98,"*Разработка сайта / бэкенд*") -> 3 | C25: =COUNTIFS('Вопросы'!$H$2:$H$98,"*Разработка сайта / бэкенд*",'Вопросы'!$J$2:$J$98,"Да") -> 0 | D25: =COUNTIFS('Вопросы'!$H$2:$H$98,"*Разработка сайта / бэкенд*",'Вопросы'!$J$2:$J$98,"Частично") -> 1 | E25: =COUNTIFS('Вопросы'!$H$2:$H$98,"*Разработка сайта / бэкенд*",'Вопросы'!$J$2:$J$98,"Нет") -> 2
A26: Автор БТ (редакторская правка) | B26: =COUNTIF('Вопросы'!$H$2:$H$98,"*Автор БТ (редакторская правка)*") -> 0 | C26: =COUNTIFS('Вопросы'!$H$2:$H$98,"*Автор БТ (редакторская правка)*",'Вопросы'!$J$2:$J$98,"Да") -> 0 | D26: =COUNTIFS('Вопросы'!$H$2:$H$98,"*Автор БТ (редакторская правка)*",'Вопросы'!$J$2:$J$98,"Частично") -> 0 | E26: =COUNTIFS('Вопросы'!$H$2:$H$98,"*Автор БТ (редакторская правка)*",'Вопросы'!$J$2:$J$98,"Нет") -> 0
A28: Как читать таблицу
A29: • Источник «БТ (Google Doc) — комментарий»: вопросы из комментариев к старым бизнес-требованиям. Ссылка открывает документ сразу на нужном комментарии (параметр disco=ID комментария).
A30: • Источник «Док. Вопросы Екатерины Лемешевой»: вопросы и ответы из вложенного файла «Вопросы по ответу Марии». Ссылка ведёт на БТ в целом; связка с БТ — в колонке «Раздел БТ».
A31: • Колонка «Раздел БТ (связка)» для комментариев сопоставлена по содержанию комментария и месту в документе (Google Drive не отдаёт точный якорь комментария), поэтому для отдельных строк раздел указан ориентировочно.
A32: • «Есть ответ»: Да — ответ дан по сути; Частично — ответ есть, но решение не финализировано или закрыта только часть вопроса; Нет — ответа нет либо ответ отложен («уточню 31.08»).
A33: • «Кому адресован (функция-ответчик)» — предлагаемая функция, которая должна дать ответ (первая — основная, далее — соисполнители). Разрез по функциям в сводке считает вопрос в каждой из указанных функций.
A34: • «Статус треда» для комментариев — статус в Google Doc (Открыт/Решён); для документа Е. Лемешевой — Закрыт, если ответ полный.
A35: • Источник БТ: https://docs.google.com/document/d/1rZKCC6zf38xjrW-WQuvGZcEYEMoMK7TBrHrj91QzOpA/edit
A36: • Дата выгрузки: 04.09.2026.

Sheet Бухгалтерияфинансы
C1: Бухгалтерия
A2: Опишите по шагам, что происходит с момента появления возврата в реестре 1С до момента, когда деньги ушли клиенту: кто что делает и в какой системе. | C2: Каждый день выгружаются из 1С два отчета по возвратам за предыдущий день. Это возвраты магазины и возвраты склада. После выгрузки отчетов, данные заносятся в гугл таблицу. Реестр склада и реестр магазины.После выгрузки, сотрудники, которые занимаются возвратами денежных средств берут реестры в работу и начинают их обрабатывать и отправлять денежные средства. Также каждый день обрабатываем реестр дружбы. Есть еще возвраты заребежные(но у данных возвратов отдельный реестр и система, данных возвратов в 1С и срм нет, у них свой отдельный ЛК) По вторникам и пятницам выгружаем отчет из 1С по отказным заказам и также берем в работу на отбработку и отправку денежных средств. | E2: 1 сценарий: заявление - приёмка -возврат ДС 2 сценарий: заявление - возврат ДС (до приёмки) 3 сценарий: заказ клиента - возврат ДС (недоотгрузка, отказ от получения)
A3: Кто физически выполняет возврат в кабинете мерчанта? Сколько человек и сколько времени на одну операцию? | C3: На участке возвратов работает 4 человека. На одну операцию в среднем уходит 15 мин. С учетом проверки самого возврата во всех системах (1С, СРМ, заявление на возврат)
A4: По какому графику выполняются возвраты — только будни? Что в праздники и в последние дни месяца? | C4: Все переводы денежных средств оформляются по графику работы сотрудников. График у сотрудников 5/2. Cуббота и воскресенье выходные. Банк в выходные также не работает, выгрузка возвратов которые были созданы, через расчетный счет, проходит только в будни в операционное время работы банка. В период распродаж, например, на зимнюю распродажу при необходимости в помощь подключаем доп.сотрудников. В новогодние каникулы выходим в доп.смены.
A5: Как узнаёте, что возврат завис: товар принят, деньги не вернули? Есть контроль или всплывает по обращению клиента? | C5: В основном о заказах, по которым не прошел вовремя возврат, поступает информация от дружбы, а им в свою очередь пишет клиент. После этого уже выясняем в чем причина, не принят был возврат складом или тех. сбой и в системе статус не прогузился корректный.
A7: Что для вас является основанием выплатить деньги клиенту: заявление, реестр 1С, отчёт, что-то ещё? | C7: Основанием является заполненное заявление на возврат от клинета. В 1С должны быть сформированы все проводки(Оплата от клиента, документ возврата, приходный ордер) чтобы корректно оформить перевод дс
A8: Достаточно ли записи в системе и данных в отчёте, или нужен документ-файл как приложение к операции? | C8: Нужны корректные данные в заявлении (электронном). Достаточно отчёта
A9: Что предъявляете при налоговой или аудиторской проверке по возврату? Какой комплект должен собираться? | B9: Нужен ли? | C9: заявление на возврат от клиента, чек на возврат
A10: Нужен акт приёмки изделия от склада или достаточно статуса в системе? | C10: Достаточно корректной статусной модели
A11: Кто и в какой момент пробивает чек «возврат прихода»? Деньги идут через кабинет мерчанта — как при этом формируется фискальный чек и кто за это отвечает? | C11: На различные компенсации (компенсации ремонта, независимой экспертизы, доставки) чек формируется в ручную в 1С на основании списания безналичных денежных средств. Если возвртат был по Юкассе, Яндекс СБП чек уходит автоматом, после проведения перевода денежных средств. Если возврат был оформлен через расчетный счет, то чеки мы сверяем. Каждый день выгружаем отчет по чекам (именно по списанием) и сверяем, чтобы чеки ушли корректно и ничего не упустили. | D11: дата чека равна дате возврата дс клиенту. Чеки на возврат по сервису bnpl формируется из двух показателей: загруженный взаимозачет и свормироанный документ в 1с на возврат товара. Поэтому система ждем чаще всего документа возварта для пробития чека. Чеки на возварт предоплаты формируется в момет загрузки взаимозачета. С помощью отчета отслеживаются в течение месяца сформированные чеки на возвраты по всем видам оплаты
A13: Допустимо ли инициировать возврат в момент приёмки в магазине, до того как изделие придёт на склад? Что для этого нужно с вашей стороны? | C13: возвраты сейчас оформляются магазинами момент приемки товара
A14: Какой риск, если деньги вернули, а изделие не дошло до склада или не прошло экспертизу? Как это отрабатывается сейчас? | C14: Рост задолженности клиентов перед компанией. Если документ возврата не будет через 3 года по истечению срока исковой давности спишем Отрабатываеться устным запросом от бухгалтерии по каждому документу возврата: оформляем отчет и напарвляем складу и ставим задачу | D14: Вопрос поднимала здесь - решения пока нет https://mattermost.12stz.com/12storeez/pl/bkt36pxmdfn5zpj566kffmi9jo
C15: Список не принятых возвратов , причины разные не доехал твоар, путаница в номенклатуре, системная ошибка статуса ВМС ит.д. Не принятые возвраты за июль 2026.xlsx | D15: Примеры задач по непринятым вовзратам https://tracker.yandex.ru/SUP-95383 https://tracker.yandex.ru/SUP-95384
A16: Есть ли сумма, выше которой возврат требует отдельного согласования? | C16: нет, если возврат клиенту согласован, то возвращается полная стоимость товара
A19: Планируем такой состав: номер заказа и возврата, клиент, признак FnF, позиции и сумма, способ оплаты, канал и точка приёмки, статус и даты статусов, признак аномалии и причина, факт/способ/дата/сумма выплаты, ссылка на заявление. Чего не хватает, чтобы работать только по отчёту?
A20: В каком виде удобнее — Qlik, выгрузка из 1С, файл? Как часто обновлять? | C20: 1С | D20: Из СРМ для сверки заказов мы берем следующие данные: 1)Комментарии оставленные от дружбы(в комментариях прописывают, про различные обмены, переносы оплат или что возврат необходим по реквизитам, комментарии также могут быть, что дс не возвращать, что дс зачтены в счет долга по другому заказу) 2) В файлах в СРМ мы также проверям прикрепленные документы( Заявления на возврат, чеки от клиентов на возврат компенсаций, реквизиты клиентов) 3) Сверяем артикула в срм (Бывает сложные ситуации с заказами, когда возникает путаница, клиент вернул одно, по системам принято другое. Соответственно, разница с принятыми артикулами в СРМ и 1С расходится, поэтому начинаем сверять и выяснять, что по факту клиент вернул
A21: Нужен отдельный срез «к выплате сегодня» или фильтруете сами?
A22: Нужен срез по периодам под закрытие месяца?
A23: Кому из бухгалтерии нужен доступ к отчёту? | C23: Есина Мария (М. Подгорняк: у меня вопрос, что это за отчет? Это аналог нынешних реестров?)
A25: Как сейчас сверяете возвраты с выписками банка и отчётами эквайера? Сколько это занимает? | C25: Есина Мария (в разрезе чеков после загрузки мною Юмани и загрузкой Морозовой НВ взаимозачетов, если это месячная сверка чеков то может занимать более 2-3 часов в день, если проверка отчетами на ежедневной основе при условии, что все загружено занимает не много времени)
A26: Что в этой сверке сломается при росте объёма возвратов? | C26: в этом году отладили процес сверки, как таковых поломок нет
A27: Какие расхождения встречаются регулярно и какие можно закрывать автоматически? | C27: 1. снйчас основаная проблема со скидками: ошибка в установлении скидки в заказе и РТиУ, сумма товара возврата равна РТиУ. Расхождения связанные со сидками, если сумма заказа не равна сумме дс от клиента, то вся цепочка рту-возврат будет не верная и тут есть риск, что команда возвратов вернет дс по не верному документу возварту. ТУт очень большая проблема и постоянные расхождления: от чего сумма возврата может быть не верной в чеке и в документе возврата 2. Чеки пробиваются автоматически, бывают случаи сбоя, но они выявляются и устраняются в ручном режиме, занимает много времени. | D27: Обсуждаем здесь https://mattermost.12stz.com/12storeez/pl/3t85hmpa8prk3y54c71gmw5zgh Постоянные не верные доработки и от этого очень много ошибок - првим руками. В мае был сбой На сегодня с новой доработкой опять проблемы - почему-то 1С сама создает возвраты ДС клиентам на скидки https://mattermost.12stz.com/12storeez/pl/13pmgc7defbdxysxpyp7urdd3y
A29: Возврат денег
A30: Наличные: как оформляется РКО, нужен паспорт, есть ограничения по сумме? Верно, что наличными за оплату картой вернуть нельзя? | C30: возврат наличными проводится ровно на ту сумму, которую клиент оплатил наличными при покупке. Выдача наличных при оплате безналичными запрещена. Клиент имеет право не предоставлять паспортные данные при любом типе возвратов
A31: Сертификат: технически можно зачислить возврат на сертификат и как это проводится в учёте? | C31: нет. Только деньгами
A32: Бонусы: как пересчитываются при частичном возврате и где это ломается? | C32: возврат проводится по стоимости товара в заказе, бонусы распределены пропорционально всем товарам
A33: «Долями» / «Подели»: как отрабатывается возврат по рассрочке? | B33: В 1С смотрим каким способом была оплата у клиента, если это сервис Долями, Сплит или Подели , то переводы дс оформляются в личном кабинете данных сревисов. Если заказ даавний(больше месяца), то по таким заказам дс переводим на расчетный счет если клиент указал реквизиты, либо пишем девочкам из дружбы, чтобы уточнили у клента как именно необходимо вернуть дс, (если рассрочка закрыта уже, то по реквизитам возвращаем, а если нет, то через сервис)
A34: Частичный возврат: как распределяется скидка и доставка? | C34: скидка пропорциональна количеству товара в заказе, стоимость доставки не всегда компннсируется при этом, так как в большинстве случаев услуга оказана, т.е. сумма возврата соответсвует стоимости в реализации по позиционно
A35: Расхождение суммы — клиент ждёт одну, возвращаем другую из-за бонусов или сервисного сбора. Кто решает и как оформляет? | B35: Вопрос скидок очень актуален, после ошибок мая были случаи, когда дс вернули больше клиенту, чем надо или наоборот. Решает команда возвартов.
A36: Что если клиент не дал реквизиты и деньги вернуть некуда? Есть срок, после которого сумма списывается? | B36: Если клиент не предоставил реквизиты в заявлении на возврат, а оплата у клиента была наличными или безналичным наложенным платежом(при данном способе оплаты обязательно необходимы реквизиты от клиента) заносим такие заказы в гугл таблицу "запрос реквизитов" девочки из дружбы их берует в работу и связываются с клинтом и как только клиент предоставляет реквизиты оформляем перевод дс
A38: Второй этап интеграции
A39: Что должно оставаться ручным всегда: исключения, крупные суммы, спорные кейсы? | C39: спорные кейсы, исключения
A40: Какой статус и какие данные система должна вернуть, чтобы вы считали операцию завершённой? | C40: пробитие чека по операции возврата, факт поступления товара на склад/магазин и схлопнутые взаиморасчеты в рамказ Клиент/Заказа, подтверждение оплаты
A43: Обратная логистика
A44: Оплата обратной доставки при возврате качественного товара — на клиенте или на нас? Как отражается в учёте и удерживается ли из суммы возврата? | C44: на клиенте
A45: При отказе в возврате изделие едет клиенту обратно — за чей счёт и как проводится?
A47: Калининград/другие регионы
A48: Клиент оплачивает доставку до нас? как мы компенсируем? или не компенсируем? | C48: компенсация на усмотрение команды дружбы
A51: Про закрытие периода
A53: В каком периоде отражается возврат: по дате приёмки, по дате выплаты или по дате документа в 1С? | C53: по дате отражения в 1С документа возврата | D53: скинуть ссылку на матрмост
A54: Что если товар принят 30-го, а деньги вернули 3-го числа следующего месяца — это разные периоды? | C54: товар учитывается по дате принятия
A55: Какой cut-off у закрытия месяца: до какого числа и часа возвраты попадают в текущий период?
A56: Есть дни, когда возвраты нельзя проводить из-за закрытия? Что тогда происходит с клиентом?
A57: Как оформляется возврат по заказу из уже закрытого периода? А по заказу прошлого года? | C57: возврат можно провести из заказа за любой период
A58: Есть крайний срок, после которого возврат по старому заказу технически не провести? | C58: могут возникнуть проблемы из-за маркировки в некоторых случаях по очень старым заказам
A59: Нужны корректировочные документы (УКД, корректировочный счёт-фактура) и кто их формирует? | B59: Нужен ли?
A60: Как возврат влияет на выручку периода и НДС | B60: Нужен ли?

Sheet РитейлМагазины 
A1: Общее | B1: ответы
A2: Опишите по шагам, что делает сотрудник, когда клиент приносит возврат: сейчас — для покупки в магазине и для онлайн-заказа. Где различия? | B2: провели встречу
A3: В какой системе проводится возврат? есть ли зависимоть от каких-либо условий | B3: 1С КА - для ИМ, 1С Р для чековых продаж(ЭБронирование)
A4: Сколько времени занимает один возврат на кассе? Что в этом времени самое долгое? | B4: замер у Клика, все где расчетный счет, и если клиент потерял КМ, заполнение заявления вручную
A5: Сколько возвратов в день в среднем и в пик по магазину? Есть часы, когда возврат создаёт очередь? | B5: в среднем 3 возврата в день всего(ИМ+Р)
A6: Кто в магазине имеет право принимать возврат — любой продавец, только администратор? | B6: любой сотрудник, если брак то администрация
A7: Что сотрудник делает сейчас с бумажным заявлением: где хранит, куда передаёт, как часто? | B7: сканируют в бухгалтерию, потом отправляют в архив
A8: Какие вопросы клиентов по возвратам чаще всего приходят в магазин, хотя решаются не в магазине? | B8: дружба при нарушении сроков возврата и брака
A10: QR код
A11: Чем производится сканирование и сможем ли использовать тот же инструмент для приемки возвратов | B11: ручным сканером
A12: Где сотрудник видит результат сканирования: в кассовой программе, в отдельном интерфейсе, в Retail CRM? Что вообще умеет касса в части приёмки возврата? | B12: 1С КА - для ИМ, 1С Р для чековых продаж(ЭБронирование), касса создает поток документов по возврату и чек
A13: Нужно ли сотруднику видеть данные клиента и состав заказа целиком или достаточно позиций к возврату? | B13: Мы сейчас видим и заказ и все товары, надо так оставить, надо видеть данные клиента и расчетный счет
A15: Приёмка и экспертиза в магазине — это одно действие или два? Между «взял изделие» и «подтвердил приёмку в системе» есть временной лаг? | B15: Принять на экспертизу вне системы, по результату оформляется возврат или отказ
A16: Кто и по каким критериям определяет следы носки, комплектность, соответствие артикула? Есть ли инструкция или это опыт сотрудника? | B16: Есть инструкция в академии
A17: Должны ли правила экспертизы в магазине совпадать с правилами склада? Сейчас они одинаковые? | B17: Склад не проводит экспретизу и не видит заводской/склад брак
A18: Сколько времени занимает осмотр изделия и что делать, если очередь? | B18: Ждать, 1м на изделие
A19: Проверяете ли сейчас коды маркировки при возврате? Если клиент купил две одинаковые вещи разными заказами — как определяете, какая именно возвращается? | B19: ДА, проверяем и печатаем если утерян, вся инфа есть в заказе
A20: Нужно ли сотруднику фотографировать изделие при приёмке — например, при сомнениях в состоянии? | B20: Такого правила нет, только если продавец сомневается он может отправить УМ
A22: Что сейчас остаётся у клиента после сдачи изделия в магазине? Второй экземпляр заявления, чек, ничего? | B22: ничего, если клиент наставивает то Заявление
A23: Что клиент должен получить в целевом процессе — электронное подтверждение приёма, распечатанную квитанцию, ничего? | B23: ИМ - квитанцию, Розница - чек, слип
A24: Как клиенты реагируют, когда на руках не остаётся никакого документа? Были конфликты? | B24: Плохо и негативно
... A62: Можем ли сделать вариант, когда клиент просто оформляет возврат и приходит в любой удобный магазин? | B62: клиент должен иметь возможность оформить заявку на возврат по любому чеку магазина, и 1с Р должна иметь возможность формировать заявку на возврат в приложении клиента. Вовзарт на рс работает в любом магазине сети

Sheet Temp
A1: № | B1: Источник | C1: Раздел БТ (связка) | D1: Ссылка | E1: Дата | F1: Кто задал | G1: Направление | H1: Кому адресован (функция-ответчик) | I1: Вопрос | J1: Есть ответ | K1: Кто ответил | L1: Ответ
A2: Вопросы по изменению заявки на возврат
A3: 1 | B3: БТ (Google Doc) — комментарий | C3: 6.1 Оформление возврата онлайн / FR-1.4 (отмена возврата) | D3: Открыть комментарий | E3: 28.08.2026 | F3: Мария Мезинова | G3: 1С / товародвижение | H3: Юля Завьялова/Света Варцаба | I3: Мы будем давать возможность корректировки возврата после создания? Или в случае корректировки старый будем удалять и создавать новый? | J3: Нет
A4: 44 | B4: БТ (Google Doc) — комментарий | C4: 3.1 Генерация QR-кода возврата | D4: Открыть комментарий | E4: 27.08.2026 | F4: Екатерина Лемешева | G4: Аналитик МП / сайт | H4: Юля Завьялова/Света Варцаба | I4: То есть, если клиент хочет поменять способ возврата (например, с 5POST на СДЭК), он должен сначала отменить текущую заявку и затем создать новую с новым способом, верно? | J4: Нет | L4: Екатерина Лемешева - в MVP, отменяем первую заявку (в ней скрываем блок штрих-код/QR-код чтобы клиент случайно не показал в канале возврата не то что требуется).Создает новую заявку с нужным ему каналом возврата и новым сформированым штрих-код/QR-код, когда ТК подтвердит заявку и мы получим обновленный статус, например, "Заявка на возврат принята".
A5: 80 | B5: Док. «Вопросы Екатерины Лемешевой» — вопр. 9 | C5: 6.4 Курьерская доставка | D5: Открыть БТ | F5: Екатерина Лемешева | G5: Аналитик МП / сайт | H5: Артем Лисин - для транспортных (их возможности) Юля Завьялова/Света Варцаба - для магазинов | I5: До какого момента клиент может самостоятельно изменить выбранную дату передачи товара в рамках той же заявки? Или создаем новую, т к данные переданы в ТК? | J5: Частично | K5: Ответ в документе (бизнес; автор в документе не указан) | L5: В рамках 14 дней на возврат после получения заказа (для F&F — 30). Конкретное ограничение (в день передачи / накануне до определённого времени) не задано.
A6: Внутренние технические вопросы
A7: 3 | B7: БТ (Google Doc) — комментарий | C7: 7.2 FR-2.6 Интеграция склада с курьерской компанией | D7: Открыть комментарий | E7: 28.08.2026 | F7: Мария Мезинова | G7: 1С / товародвижение | I7: Так мы 1С с курьерскими компаниями интегрируем или систему склада? | J7: Частично | K7: Светлана Варцаба | L7: Как я понимаю, мы 1С интегрируем, и Бетта на своей стороне тоже должна будет сделать какую-то доработку.
A8: 7 | B8: БТ (Google Doc) — комментарий | C8: 7.8 FR-8.5 Интеграции с партнёрами доставки / 6.12 | D8: Открыть комментарий | E8: 27.08.2026 | F8: Мария Мезинова | G8: 1С / товародвижение | I8: В какой момент должна срабатывать интеграция 1С-ТК? На каком этапе возврата? | J8: Нет
A9: 9 | B9: БТ (Google Doc) — комментарий | C9: 6.4 Канал — курьерская доставка (окно с информацией о возврате) | D9: Открыть комментарий | E9: 26.08.2026 | F9: Мария Мезинова | G9: 1С / товародвижение | I9: В каком статусе в этот момент должен быть документ возврата? | J9: Нет
A10: 20 | B10: БТ (Google Doc) — комментарий | C10: 6.7 Канал — Почта России (накладную отправят на email) | D10: Открыть комментарий | E10: 26.08.2026 | F10: Елена Васильева | G10: Tech-аналитик (сайт / интеграции) | I10: Отправка накладной на email будет происходить вручную или автоматически? | J10: Нет
A11: 24 | B11: БТ (Google Doc) — комментарий | C11: 6.11 CSI и обратная связь | D11: Открыть комментарий | E11: 26.08.2026 | F11: Елена Васильева | G11: Tech-аналитик (сайт / интеграции) | I11: [tech] Должна быть интеграция с платформой Отзывов, чтобы результаты опроса приходили на платформу. | J11: Нет
A12: 25 | B12: БТ (Google Doc) — комментарий | C12: 3.1 / 6.7 Почта России (список филиалов) | D12: Открыть комментарий | E12: 28.08.2026 | F12: Елена Васильева | G12: Tech-аналитик (сайт / интеграции) | I12: [tech] Список филиалов Почты РФ должен приходить из сервиса Логистики? Дополнено 28.08: в макетах нет выбора филиала почты, указано, что клиент может отнести в любой ближайший. То есть список филиалов выводить не нужно? | J12: Нет
A13: 40 | B13: БТ (Google Doc) — комментарий | C13: 11 Отчётность — текущий статус и даты событий | D13: Открыть комментарий | E13: 26.08.2026 | F13: Артём Колосов | G13: Архитектор | I13: Выводим текущий статус и его дату изменения, или все возможные статусы и даты их установки? | J13: Нет
A14: 49 | B14: БТ (Google Doc) — комментарий | C14: 6.5 5POST — уведомление о принятой посылке | D14: Открыть комментарий | E14: 27.08.2026 | F14: Екатерина Лемешева | G14: Аналитик МП / сайт | I14: Получает от 5post или от нас? (Елена Васильева: если отправляет 5post, нужны ли настройки на их стороне?) | J14: Частично | K14: Светлана Варцаба | L14: Уточним с коллегами, что будет дешевле (нам самим отправить или через ПВЗ), но вообще лучше, чтобы от нас приходило.
A15: Статусная модель
A16: 6 | B16: БТ (Google Doc) — комментарий | C16: 10 Статусная модель возврата | D16: Открыть комментарий | E16: 27.08.2026 | F16: Мария Мезинова | G16: 1С / товародвижение | H16: Юля Завьялова/Света Варцаба/Оля Соколова | I16: Нужна статусная модель по всем системам, включая ТК и 3PL. Желаемые статусы нужно наложить на физический процесс и статусы партнеров. | J16: Частично
A17: 28 | B17: БТ (Google Doc) — комментарий | C17: 3.1 Приёмка и экспертиза; возврат ДС | D17: Открыть комментарий | E17: 26.08.2026 | F17: Артём Колосов | G17: Архитектор | H17: Юля Завьялова/Света Варцаба/Оля Соколова | I17: 1. Нужна ли интеграция с ТК/ПВЗ по статусам, если мы эту информацию клиенту не отображаем? 2. Что происходит, если изделие не прошло экспертизу и мы не принимаем возврат? Что делаем, если аномалия: в заявлении одно изделие, а по факту другое? | J17: Нет | L17: Предложите решение
A18: 29 | B18: БТ (Google Doc) — комментарий | C18: 6.8 Статусы возврата / 10 Статусная модель | D18: Открыть комментарий | E18: 27.08.2026 | F18: Артём Колосов | G18: Архитектор | H18: Юля Завьялова/Света Варцаба/Оля Соколова | I18: 1. Между «Создан» и «На экспертизе» должен быть статус для ТК/ПВЗ/5POST (напр. «В пути»). 2. Статус «Принят» неинформативен, как будто финальный. 3. До «Выполнен» отдельно «ДС возвращены», далее по таймеру закрывать. 4. Что по физике процесса при отклонении возврата? 5. Нужны ли промежуточные статусы от ТК по доставке? | J18: Частично | K18: Екатерина Лемешева; Светлана Варцаба | L18: Екатерина: согласна, нужен статус «Клиент передал товар» → «Товар в пути до склада» → «На экспертизе». Светлана: «Тут блок перепишем».
A19: Причины возвратов
A20: 26 | B20: БТ (Google Doc) — комментарий | C20: 3.1 Причины возврата | D20: Открыть комментарий | E20: 03.09.2026 | F20: Елена Васильева | G20: Tech-аналитик (сайт / интеграции) | H20: Дарья Ким | I20: 1. [tech] Откуда будут приходить причины возврата? 2. Должны ли они где-то настраиваться? | J20: Частично | K20: Светлана Варцаба; Елена Васильева | L20: Светлана: @r.pushkar — где можем настраивать причины возврата, можем ли дать настройку в админке? Елена (03.09): в админке сайта уже есть группы возврата (1-й уровень) и причины (2-й уровень) — предложение использовать готовый функционал и брать причины из админки сайта.
A21: 62 | B21: БТ (Google Doc) — комментарий | C21: 3.1 Причины возврата | D21: Открыть комментарий | E21: 01.09.2026 | F21: Мария Мезинова | G21: 1С / товародвижение | H21: Дарья Ким | I21: Будут ли передаваться причины возврата в 1С? | J21: Нет | L21: Предложите решение, не понятно для чего это нужно
A28: Вопросы к бизнес-заказчику
A29: 13 | B29: БТ (Google Doc) — комментарий | C29: 3.1 Функционал Дружбы в RCRM / 9 Интеграции (CRM) | D29: Открыть комментарий | E29: 27.08.2026 | F29: Мария Мезинова | G29: 1С / товародвижение | H29: Здесь Бизнес заказчик не ответит, здесь нужно предложение - насколько я услышала от Виталия - это 1С | I29: Сейчас мы принимаем RCRM как мастер-систему, все спорные кейсы всегда проверяем и сравниваем именно с ней. Какую систему рассматриваем как мастер-систему в этом проекте? | J29: Нет | K29: Светлана Варцаба | L29: Здесь не понимаю, приведи пример, пожалуйста.
A30: 16 | B30: БТ (Google Doc) — комментарий | C30: 8 NFR-1 Пиковая нагрузка (всплеск после выходных) | D30: Открыть комментарий | E30: 26.08.2026 | F30: Елена Васильева | G30: Tech-аналитик (сайт / интеграции) | H30: Оля Соколова/Лариса Прокопенко | I30: Какие максимальные значения сейчас наблюдаются после выходных? В пункте 5.1 шаг 1 указывалось 50–80 заявлений, то есть примерно такое кол-во? | J30: Нет
A31: 19 | B31: БТ (Google Doc) — комментарий | C31: 6.7 Канал — Почта России (клиент оплачивает расходы по доставке) | D31: Открыть комментарий | E31: 26.08.2026 | F31: Елена Васильева | G31: Tech-аналитик (сайт / интеграции) | H31: Бизнес-заказчик / владелец процесса возвратов | I31: Хотелось бы уточнить, оплата доставки на стороне клиента? | J31: Нет
A32: 35 | B32: БТ (Google Doc) — комментарий | C32: 5.4 Проблемы клиента (возврат ДС и оформление) | D32: Открыть комментарий | E32: 26.08.2026 | F32: Артём Колосов | G32: Архитектор | H32: Варцаба Света | I32: Как эти проблемы устранит целевой процесс? | J32: Нет
A33: 87 | B33: Док. «Вопросы Екатерины Лемешевой» — вопр. 16 | C33: 10 Статусная модель | D33: Открыть БТ | F33: Екатерина Лемешева | G33: Аналитик МП / сайт | H33: Завьялова Юля / Света Варцаба | I33: Если после окончания конечного срока предоставляется дополнительное время — сколько оно составляет? | J33: Частично | K33: Ответ в документе (бизнес; автор в документе не указан) | L33: Везде должен быть срок отправки (дополнительное время не предусмотрено — следует из ответа 15).
A34: 96 | B34: Док. «Вопросы Екатерины Лемешевой» — вопр. 24.1 | C34: 7.5 Приёмка и экспертиза | D34: Открыть БТ | F34: Екатерина Лемешева | G34: Аналитик МП / сайт | H34: Оля Соклова | I34: На каком этапе считаем, что брак подтверждён и доставка возврата оплачивается продавцом: по выбранной клиентом причине или только после проверки/экспертизы? | J34: Нет
A35: 97 | B35: Док. «Вопросы Екатерины Лемешевой» — вопр. 24.2 | C35: 7.5 FR-5.3 / 5.4 | D35: Открыть БТ | F35: Екатерина Лемешева | G35: Аналитик МП / сайт | H35: Оля Соклова | I35: Если клиент выбрал причину «брак», но по итогам проверки брак не подтвердился — что с оплатой доставки и с процессом в целом? | J35: Частично | K35: Ответ в документе (бизнес; автор в документе не указан) | L35: Обратиться к Оле Соколовой; на первом этапе оставляем решение как есть сейчас.
A36: 99 | B36: Док. «Вопросы Екатерины Лемешевой» — вопр. 26 | C36: 6.7 Канал — Почта России (расходы по доставке) | D36: Открыть БТ | F36: Екатерина Лемешева | G36: Аналитик МП / сайт | H36: Оля Соклова | I36: Как компенсировать клиенту из Калининграда расход на самостоятельную отправку через Почту России при возврате по браку? (кто платит изначально, как узнаём стоимость, нужен ли чек, способ и момент компенсации, инструкция в карточке возврата) | J36: Нет
A37: 58 | B37: БТ (Google Doc) — комментарий | C37: 6.9 Возврат ДС — Бонусы | D37: Открыть комментарий | E37: 31.07.2026 | F37: Светлана Варцаба | G37: Владелец БТ / РП | H37: Оля Соклова | I37: Нужно, чтобы автоматически возвращались бонусы; много проблем, так как скидки в разных местах. | J37: Нет
A38: 28 | B38: БТ (Google Doc) — комментарий | C38: 3.1 Приёмка и экспертиза; возврат ДС | D38: Открыть комментарий | E38: 26.08.2026 | F38: Артём Колосов | G38: Архитектор | H38: Артем Лисин | I38: 1. Нужна ли интеграция с ТК/ПВЗ по статусам, если мы эту информацию клиенту не отображаем? 2. Что происходит, если изделие не прошло экспертизу и мы не принимаем возврат? Что делаем, если аномалия: в заявлении одно изделие, а по факту другое? | J38: Нет | L38: Предложите решение
A39: 31 | B39: БТ (Google Doc) — комментарий | C39: 7.3 FR-3.3 Аутлет / «Цветной» | D39: Открыть комментарий | E39: 26.08.2026 | F39: Артём Колосов | G39: Архитектор | H39: Варцаба Светлана/ Завьялова Юля | I39: Если клиент придёт в магазин с покупкой из аутлета — мы его разворачиваем? | J39: Нет
A40: Клиентский сервис + заказчик
A41: 38 | B41: БТ (Google Doc) — комментарий | C41: 3.1 Функционал Дружбы в RCRM | D41: Открыть комментарий | E41: 27.08.2026 | F41: Артём Колосов | G41: Архитектор | H41: Клиентский сервис (Дружба, Retail CRM) | I41: Где-то есть его описание? Как видим процесс, что нужно доработать? | J41: Нет | K41: Светлана Варцаба | L41: Здесь я уточню 31.08 с Retail CRM.
A42: 42 | B42: БТ (Google Doc) — комментарий | C42: 6.10 Обмен / 7.7 | D42: Открыть комментарий | E42: 26.08.2026 | F42: Артём Колосов | G42: Архитектор | H42: Клиентский сервис (Дружба, Retail CRM) Бизнес-заказчик / владелец процесса возвратов | I42: Из этого непонятно, меняется ли что-то в функционале обмена. Нужно ли для FnF менять что-то в обмене, если будут изменения в возврате? | J42: Нет | L42: не меняем процесс обмена в итерации 1
A43: 54 | B43: БТ (Google Doc) — комментарий | C43: 3.1 Обмен (онлайн — для FnF) | D43: Открыть комментарий | E43: 31.07.2026 | F43: Светлана Варцаба | G43: Владелец БТ / РП | H43: Клиентский сервис (Дружба, Retail CRM) Бизнес-заказчик / владелец процесса возвратов | I43: Онлайн обмен для всех, а не только для ФФ. | J43: Нет
A44: 55 | B44: БТ (Google Doc) — комментарий | C44: 6.10 Обмен / 9 CRM (признак FnF) | D44: Открыть комментарий | E44: 31.07.2026 | F44: Светлана Варцаба | G44: Владелец БТ / РП | H44: Клиентский сервис (Дружба, Retail CRM) Бизнес-заказчик / владелец процесса возвратов | I44: Как мы определим ФФ (если они у нас в гугл-таблице)? | J44: Нет
A45: 56 | B45: БТ (Google Doc) — комментарий | C45: 6.9 Возврат денежных средств | D45: Открыть комментарий | E45: 31.07.2026 | F45: Светлана Варцаба | G45: Владелец БТ / РП | H45: Клиентский сервис (Дружба, Retail CRM) Бизнес-заказчик / владелец процесса возвратов | I45: Идеальный сценарий — у нас есть личный счёт клиента. | J45: Нет
A46: 57 | B46: БТ (Google Doc) — комментарий | C46: 6.10 Обмен | D46: Открыть комментарий | E46: 31.07.2026 | F46: Светлана Варцаба | G46: Владелец БТ / РП | H46: Клиентский сервис (Дружба, Retail CRM) Бизнес-заказчик / владелец процесса возвратов | I46: Нужно сделать, чтобы можно было поменять — подумать, как сделать как в ЦУМе (вернуть и доплатить). | J46: Нет
A48: Склад
A49: 2 | B49: БТ (Google Doc) — комментарий | C49: 7.5 FR-5.2 Результат экспертизы фиксируется в системе | D49: Открыть комментарий | E49: 27.08.2026 | F49: Мария Мезинова | G49: 1С / товародвижение | H49: Склад | I49: Сейчас при получении данных в 1С о возврате мы от Беты получаем только кондицию брак или недостачи. | J49: Нет
A50: 41 | B50: БТ (Google Doc) — комментарий | C50: 3.1 Автосверка манифеста | D50: Открыть комментарий | E50: 28.08.2026 | F50: Артём Колосов | G50: Архитектор | H50: Склад Бухгалтерия | I50: Что за процесс? Что является результатом автосверки? | J50: Частично | K50: Светлана Варцаба; Мария Мезинова | L50: Светлана: сейчас сверяем манифесты и принятое складом, чтобы понять, кому пора возвращать деньги; при интеграции курьерских служб по возврату в этом нет необходимости. Мария: необходимость в сверке останется (аномалии, ошибки склада, сбой обмена с 1С) — нужен отчёт: данные манифеста vs фактически принятое на Бете.
A51: Продукт МП / сайт
A52: 76 | B52: Док. «Вопросы Екатерины Лемешевой» — вопр. 5 | C52: 3.1 Электронное заявление (шаблон) | D52: Открыть БТ | F52: Екатерина Лемешева | G52: Аналитик МП / сайт | H52: Бизнес-заказчик / владелец процесса возвратов Продукт МП / сайт | I52: Какой финальный шаблон электронного заявления используем в целевом процессе с учётом текущего заявления и примера LIME? | J52: Частично | K52: Ответ в документе (бизнес; автор в документе не указан) | L52: Катя приложила (шаблон). Финальное утверждение шаблона не зафиксировано.
A53: 47 | B53: БТ (Google Doc) — комментарий | C53: 6.7 Канал — Почта России | D53: Открыть комментарий | E53: 26.08.2026 | F53: Екатерина Лемешева | G53: Аналитик МП / сайт | H53: Бизнес-заказчик / владелец процесса возвратов; Логистика Продукт МП / сайт | I53: В макетах только для Калининграда, верно? Не совсем понятно, что требуется от нашего приложения. 1. Накладная отправляется на почту которая была указана в заказе? 2. Где генерируется накладная, откуда она отправляется? 3. Как определять дату, до которой нужно выполнить возврат? | J53: Нет | L53: Екатерина Лемешева - 1. email берем из заказа. 2. Про накладную не знаю ответа, кто ее создает? В BRD написан пункт: 6.7. Канал — Почта России В окне возврата указано, что накладную отправят на email, указанный при оформлении заказа; клиенту приходит накладная. Кто отправляет эту накладную, если он сдает на Почте? 3. Ответ получен: Калининграда / самостоятельной отправки через Почту России;(14 дней), но не понятно, как мы зафиксируем этот момент, что он его принес и отправил, если мы не интегрируемся с почтой. Если только звонок в Дружбу, чтобы они вручную изменили статус что он "В пути", чтобы по истечени времени ("от бездействия") автоматически не отменить заявку.
A54: 46 | B54: БТ (Google Doc) — комментарий | C54: 6.7 Почта России (Калининград) / 6.9 сроки возврата ДС | D54: Открыть комментарий | E54: 20.08.2026 | F54: Екатерина Лемешева | G54: Аналитик МП / сайт | H54: Бизнес-заказчик / владелец процесса возвратов; Логистика Продукт МП / сайт | I54: В случае с Почтой из Калининграда как рассчитывать срок возврата? Посылка может задержаться, и мы не успеем провести экспертизу и вернём деньги раньше. Может, явно указать на макете? (ссылка на Figma) | J54: Нет | L54: Екатерина Лемешева - Тут ответ получен, т к время отчета пойдет от момента попадания товара на наш склад, то отчет 10 дней на возврат ДС пойдет от этого момента. В оферте ссылаться на 10-дневный срок по ст. 26.1 ЗоЗПП, чтобы клиент не считал срок от момента создания заявки / заявления. Четко прописываем в МП/сайте «Обязанность продавца по возврату денежных средств считается наступившей с момента поступления товара на склад и подтверждения соответствия товара условиям возврата уполномоченным сотрудником». В Калининграде вроде открылся наш магазин
A55: 85 | B55: Док. «Вопросы Екатерины Лемешевой» — вопр. 14 | C55: 7.4 FR-4.3 Раздел «Возвраты» (сроки, блок «что дальше») | D55: Открыть БТ | F55: Екатерина Лемешева | G55: Аналитик МП / сайт | H55: Продукт МП / сайт | I55: Где и в каком виде показываем клиенту конечную дату передачи товара, если дату он не выбирает? Нужно ли сразу сообщать об автоматической отмене? | J55: Частично | K55: Ответ в документе (бизнес; автор в документе не указан) | L55: Нужно! Показывать срок на макете и предупреждать: «Передайте/отправьте товар до такой-то даты. После этой даты заявка будет отменена». Конкретное место на макете не указано.
A56: 92 | B56: Док. «Вопросы Екатерины Лемешевой» — вопр. 21 | C56: 7.4 FR-4.3 Раздел «Возвраты» | D56: Открыть БТ | F56: Екатерина Лемешева | G56: Аналитик МП / сайт | H56: Продукт МП / сайт | I56: Если да, то где на макете должна быть эта надпись / на каком этапе? | J56: Нет
A57: 73 | B57: Док. «Вопросы Екатерины Лемешевой» — вопр. 2 | C57: 6.9 Возврат ДС / 7.6 FR-6.3 | D57: Открыть БТ | F57: Екатерина Лемешева | G57: Аналитик МП / сайт | H57: Продукт МП / сайт Финансы / бухгалтерия; | I57: Относится ли минимальный набор «номер счёта + банк» к данным, которые мы запрашиваем у клиента в МП/на сайте, или только к составу электронного заявления? | J57: Частично | K57: Ответ в документе (бизнес; автор в документе не указан) | L57: Дан единый перечень реквизитов (см. вопр. 1); разделение «запрос в МП» vs «состав заявления» явно не прокомментировано.
